{
"meta":{"test_sets":[],"test_metrics":[],"learn_metrics":[{"best_value":"Min","name":"Logloss"}],"launch_mode":"Train","parameters":"","iteration_count":1000,"learn_sets":["learn"],"name":"experiment"},
"iterations":[
{"learn":[0.6397199735],"iteration":0,"passed_time":0.008127107958,"remaining_time":8.11898085},
{"learn":[0.5898201302],"iteration":1,"passed_time":0.01425984938,"remaining_time":7.115664838},
{"learn":[0.5457343228],"iteration":2,"passed_time":0.01970068721,"remaining_time":6.547195049},
{"learn":[0.498243297],"iteration":3,"passed_time":0.02531353918,"remaining_time":6.303071256},
{"learn":[0.4624000614],"iteration":4,"passed_time":0.0318446529,"remaining_time":6.337085928},
{"learn":[0.4224065928],"iteration":5,"passed_time":0.03714874805,"remaining_time":6.154309261},
{"learn":[0.3828805642],"iteration":6,"passed_time":0.04299425594,"remaining_time":6.099042306},
{"learn":[0.3519793191],"iteration":7,"passed_time":0.0495272528,"remaining_time":6.141379347},
{"learn":[0.3233648816],"iteration":8,"passed_time":0.05515266384,"remaining_time":6.072921096},
{"learn":[0.2974104944],"iteration":9,"passed_time":0.0632982832,"remaining_time":6.266530036},
{"learn":[0.2707342711],"iteration":10,"passed_time":0.06921115637,"remaining_time":6.22271215},
{"learn":[0.2499422585],"iteration":11,"passed_time":0.07534626208,"remaining_time":6.203508911},
{"learn":[0.2296590296],"iteration":12,"passed_time":0.08207171407,"remaining_time":6.23113706},
{"learn":[0.2119710367],"iteration":13,"passed_time":0.08885496882,"remaining_time":6.257928518},
{"learn":[0.1960952033],"iteration":14,"passed_time":0.09566688152,"remaining_time":6.28212522},
{"learn":[0.1808258659],"iteration":15,"passed_time":0.1017665982,"remaining_time":6.258645792},
{"learn":[0.1679615664],"iteration":16,"passed_time":0.1080721825,"remaining_time":6.249115024},
{"learn":[0.1544953606],"iteration":17,"passed_time":0.1149392976,"remaining_time":6.270577234},
{"learn":[0.1434208256],"iteration":18,"passed_time":0.1214024938,"remaining_time":6.268202441},
{"learn":[0.134733845],"iteration":19,"passed_time":0.1279381396,"remaining_time":6.268968841},
{"learn":[0.1238951621],"iteration":20,"passed_time":0.1338195262,"remaining_time":6.238538864},
{"learn":[0.1155332087],"iteration":21,"passed_time":0.1399246866,"remaining_time":6.220288341},
{"learn":[0.1075324254],"iteration":22,"passed_time":0.1470252273,"remaining_time":6.245375961},
{"learn":[0.1008702414],"iteration":23,"passed_time":0.1529408366,"remaining_time":6.219594024},
{"learn":[0.094847952],"iteration":24,"passed_time":0.1615678253,"remaining_time":6.301145186},
{"learn":[0.08928727512],"iteration":25,"passed_time":0.1691382892,"remaining_time":6.336180528},
{"learn":[0.08335688776],"iteration":26,"passed_time":0.1772977329,"remaining_time":6.389284966},
{"learn":[0.07767513597],"iteration":27,"passed_time":0.1866387699,"remaining_time":6.479031583},
{"learn":[0.07180318622],"iteration":28,"passed_time":0.1944052313,"remaining_time":6.509223435},
{"learn":[0.06678082124],"iteration":29,"passed_time":0.2000263192,"remaining_time":6.467517654},
{"learn":[0.06329996418],"iteration":30,"passed_time":0.206492738,"remaining_time":6.454563327},
{"learn":[0.05901015698],"iteration":31,"passed_time":0.2138063445,"remaining_time":6.467641922},
{"learn":[0.05558002969],"iteration":32,"passed_time":0.2197906072,"remaining_time":6.440530823},
{"learn":[0.0529199699],"iteration":33,"passed_time":0.2277331787,"remaining_time":6.47030149},
{"learn":[0.05064523119],"iteration":34,"passed_time":0.234351329,"remaining_time":6.461400927},
{"learn":[0.04769785835],"iteration":35,"passed_time":0.241578688,"remaining_time":6.468940423},
{"learn":[0.04524010502],"iteration":36,"passed_time":0.2473740922,"remaining_time":6.438412182},
{"learn":[0.04292616058],"iteration":37,"passed_time":0.253624029,"remaining_time":6.420692523},
{"learn":[0.04068635132],"iteration":38,"passed_time":0.2601957003,"remaining_time":6.411488924},
{"learn":[0.03836221704],"iteration":39,"passed_time":0.2660061825,"remaining_time":6.38414838},
{"learn":[0.03622337636],"iteration":40,"passed_time":0.2729719091,"remaining_time":6.384879532},
{"learn":[0.03408732456],"iteration":41,"passed_time":0.278779569,"remaining_time":6.358829217},
{"learn":[0.03250174727],"iteration":42,"passed_time":0.2849537082,"remaining_time":6.341876715},
{"learn":[0.0306322367],"iteration":43,"passed_time":0.2921525175,"remaining_time":6.347677426},
{"learn":[0.02880384393],"iteration":44,"passed_time":0.2992340957,"remaining_time":6.350412476},
{"learn":[0.027463809],"iteration":45,"passed_time":0.3074145207,"remaining_time":6.375509843},
{"learn":[0.02623612729],"iteration":46,"passed_time":0.3137061379,"remaining_time":6.36089254},
{"learn":[0.02509317835],"iteration":47,"passed_time":0.3212317903,"remaining_time":6.371097175},
{"learn":[0.02394962536],"iteration":48,"passed_time":0.328049515,"remaining_time":6.366838546},
{"learn":[0.02272115303],"iteration":49,"passed_time":0.3349890001,"remaining_time":6.364791001},
{"learn":[0.02184053084],"iteration":50,"passed_time":0.3421916446,"remaining_time":6.367448446},
{"learn":[0.02086778489],"iteration":51,"passed_time":0.3491803129,"remaining_time":6.365825704},
{"learn":[0.02002327948],"iteration":52,"passed_time":0.3581185191,"remaining_time":6.398834671},
{"learn":[0.01916375331],"iteration":53,"passed_time":0.3656680616,"remaining_time":6.405962709},
{"learn":[0.01847212885],"iteration":54,"passed_time":0.3744420484,"remaining_time":6.433595196},
{"learn":[0.01767945483],"iteration":55,"passed_time":0.3813966204,"remaining_time":6.429257316},
{"learn":[0.01725723443],"iteration":56,"passed_time":0.3891183354,"remaining_time":6.437519127},
{"learn":[0.0167190401],"iteration":57,"passed_time":0.3957767332,"remaining_time":6.427960046},
{"learn":[0.01607383323],"iteration":58,"passed_time":0.4043102925,"remaining_time":6.44840653},
{"learn":[0.01545074072],"iteration":59,"passed_time":0.4106352994,"remaining_time":6.433286357},
{"learn":[0.01481477473],"iteration":60,"passed_time":0.4173104344,"remaining_time":6.423844228},
{"learn":[0.01431470596],"iteration":61,"passed_time":0.4241314221,"remaining_time":6.416697966},
{"learn":[0.01380208928],"iteration":62,"passed_time":0.4305900651,"remaining_time":6.404172873},
{"learn":[0.01341657127],"iteration":63,"passed_time":0.4384631917,"remaining_time":6.412524179},
{"learn":[0.01305942201],"iteration":64,"passed_time":0.4458317895,"remaining_time":6.413118818},
{"learn":[0.01263968469],"iteration":65,"passed_time":0.4531082464,"remaining_time":6.412168214},
{"learn":[0.01223342828],"iteration":66,"passed_time":0.4592619475,"remaining_time":6.395393985},
{"learn":[0.01187218004],"iteration":67,"passed_time":0.466672687,"remaining_time":6.396160946},
{"learn":[0.01158263271],"iteration":68,"passed_time":0.4729220363,"remaining_time":6.381020518},
{"learn":[0.01125573887],"iteration":69,"passed_time":0.4792128893,"remaining_time":6.36668553},
{"learn":[0.01091328401],"iteration":70,"passed_time":0.4859144327,"remaining_time":6.357950816},
{"learn":[0.01053892025],"iteration":71,"passed_time":0.4919589938,"remaining_time":6.340804809},
{"learn":[0.01028683803],"iteration":72,"passed_time":0.4995108775,"remaining_time":6.343103882},
{"learn":[0.0101341815],"iteration":73,"passed_time":0.505939368,"remaining_time":6.331079118},
{"learn":[0.009929590599],"iteration":74,"passed_time":0.5127153798,"remaining_time":6.323489685},
{"learn":[0.009658270497],"iteration":75,"passed_time":0.5193907235,"remaining_time":6.314697743},
{"learn":[0.009415760179],"iteration":76,"passed_time":0.5256705127,"remaining_time":6.301219263},
{"learn":[0.009240530248],"iteration":77,"passed_time":0.5326195474,"remaining_time":6.295836189},
{"learn":[0.00901124174],"iteration":78,"passed_time":0.5389443518,"remaining_time":6.28313605},
{"learn":[0.008826134779],"iteration":79,"passed_time":0.5462215545,"remaining_time":6.281547877},
{"learn":[0.008683515649],"iteration":80,"passed_time":0.5527991025,"remaining_time":6.271881175},
{"learn":[0.008497467646],"iteration":81,"passed_time":0.5587782186,"remaining_time":6.255590301},
{"learn":[0.008289970018],"iteration":82,"passed_time":0.5668160276,"remaining_time":6.262292738},
{"learn":[0.008168259224],"iteration":83,"passed_time":0.5729340517,"remaining_time":6.247709421},
{"learn":[0.007987594025],"iteration":84,"passed_time":0.5792392431,"remaining_time":6.235340087},
{"learn":[0.007861936008],"iteration":85,"passed_time":0.5854595554,"remaining_time":6.222209693},
{"learn":[0.007697831446],"iteration":86,"passed_time":0.5915224279,"remaining_time":6.207585939},
{"learn":[0.00749381571],"iteration":87,"passed_time":0.5984676192,"remaining_time":6.202300781},
{"learn":[0.007357078028],"iteration":88,"passed_time":0.6045579913,"remaining_time":6.188228428},
{"learn":[0.007294029631],"iteration":89,"passed_time":0.6115537428,"remaining_time":6.183487844},
{"learn":[0.007213168799],"iteration":90,"passed_time":0.6173004613,"remaining_time":6.166221091},
{"learn":[0.007119566695],"iteration":91,"passed_time":0.6232158206,"remaining_time":6.150869185},
{"learn":[0.006992510996],"iteration":92,"passed_time":0.63040176,"remaining_time":6.148111789},
{"learn":[0.006807669409],"iteration":93,"passed_time":0.6360692882,"remaining_time":6.130625267},
{"learn":[0.006708896285],"iteration":94,"passed_time":0.6421830832,"remaining_time":6.117638845},
{"learn":[0.006600607419],"iteration":95,"passed_time":0.6488012527,"remaining_time":6.10954513},
{"learn":[0.006435299821],"iteration":96,"passed_time":0.6546706675,"remaining_time":6.094511471},
{"learn":[0.006325659461],"iteration":97,"passed_time":0.6623209654,"remaining_time":6.096056233},
{"learn":[0.00630216127],"iteration":98,"passed_time":0.6684926496,"remaining_time":6.083958356},
{"learn":[0.006184427472],"iteration":99,"passed_time":0.6750604167,"remaining_time":6.075543751},
{"learn":[0.006144249958],"iteration":100,"passed_time":0.6821247898,"remaining_time":6.071586},
{"learn":[0.006137416687],"iteration":101,"passed_time":0.688131128,"remaining_time":6.05825248},
{"learn":[0.006097181078],"iteration":102,"passed_time":0.6951515508,"remaining_time":6.053892631},
{"learn":[0.006074124158],"iteration":103,"passed_time":0.7009874422,"remaining_time":6.039276425},
{"learn":[0.005955947721],"iteration":104,"passed_time":0.7073453741,"remaining_time":6.029277236},
{"learn":[0.005836992138],"iteration":105,"passed_time":0.7138151824,"remaining_time":6.020290312},
{"learn":[0.005714523442],"iteration":106,"passed_time":0.7199605632,"remaining_time":6.008642831},
{"learn":[0.005654216577],"iteration":107,"passed_time":0.7279887707,"remaining_time":6.012647995},
{"learn":[0.005606013297],"iteration":108,"passed_time":0.7344523762,"remaining_time":6.003642819},
{"learn":[0.005538785212],"iteration":109,"passed_time":0.7416510688,"remaining_time":6.000631374},
{"learn":[0.005457644603],"iteration":110,"passed_time":0.750399292,"remaining_time":6.00995469},
{"learn":[0.005417739383],"iteration":111,"passed_time":0.7604504061,"remaining_time":6.029285363},
{"learn":[0.005324644532],"iteration":112,"passed_time":0.7677922651,"remaining_time":6.02682955},
{"learn":[0.005267303778],"iteration":113,"passed_time":0.7764883679,"remaining_time":6.034813105},
{"learn":[0.005165361127],"iteration":114,"passed_time":0.7836721242,"remaining_time":6.030868086},
{"learn":[0.005080455145],"iteration":115,"passed_time":0.7910418993,"remaining_time":6.028284819},
{"learn":[0.005011062625],"iteration":116,"passed_time":0.7988588566,"remaining_time":6.028994619},
{"learn":[0.004925290435],"iteration":117,"passed_time":0.806749137,"remaining_time":6.030107956},
{"learn":[0.004870926654],"iteration":118,"passed_time":0.8140191772,"remaining_time":6.02647811},
{"learn":[0.004857107147],"iteration":119,"passed_time":0.8222480735,"remaining_time":6.029819206},
{"learn":[0.004840583283],"iteration":120,"passed_time":0.8302258794,"remaining_time":6.031145025},
{"learn":[0.004836536122],"iteration":121,"passed_time":0.8393416309,"remaining_time":6.040507803},
{"learn":[0.004813162813],"iteration":122,"passed_time":0.8494770779,"remaining_time":6.056840629},
{"learn":[0.004764000789],"iteration":123,"passed_time":0.8587055245,"remaining_time":6.066339028},
{"learn":[0.004731107233],"iteration":124,"passed_time":0.8661763947,"remaining_time":6.063234763},
{"learn":[0.004654604239],"iteration":125,"passed_time":0.8750737747,"remaining_time":6.069956183},
{"learn":[0.004632571401],"iteration":126,"passed_time":0.884295052,"remaining_time":6.078658113},
{"learn":[0.004589259926],"iteration":127,"passed_time":0.8935869047,"remaining_time":6.087560788},
{"learn":[0.004559887932],"iteration":128,"passed_time":0.9026101692,"remaining_time":6.094367887},
{"learn":[0.004557058934],"iteration":129,"passed_time":0.910642622,"remaining_time":6.094300624},
{"learn":[0.004517009924],"iteration":130,"passed_time":0.9187260286,"remaining_time":6.094449763},
{"learn":[0.004485712718],"iteration":131,"passed_time":0.9278512663,"remaining_time":6.101324993},
{"learn":[0.00446562907],"iteration":132,"passed_time":0.9374808227,"remaining_time":6.111247168},
{"learn":[0.004439096454],"iteration":133,"passed_time":0.9447728367,"remaining_time":6.105770721},
{"learn":[0.004409317788],"iteration":134,"passed_time":0.9531645772,"remaining_time":6.107313772},
{"learn":[0.004390959558],"iteration":135,"passed_time":0.9599843733,"remaining_time":6.098724254},
{"learn":[0.004374414612],"iteration":136,"passed_time":0.9683825383,"remaining_time":6.100103143},
{"learn":[0.004359651891],"iteration":137,"passed_time":0.9756822317,"remaining_time":6.094478867},
{"learn":[0.004290024171],"iteration":138,"passed_time":0.9845098499,"remaining_time":6.098294825},
{"learn":[0.004247451126],"iteration":139,"passed_time":0.9932813638,"remaining_time":6.10158552},
{"learn":[0.004242201251],"iteration":140,"passed_time":1.007223003,"remaining_time":6.136202553},
{"learn":[0.004210672063],"iteration":141,"passed_time":1.022385519,"remaining_time":6.177512504},
{"learn":[0.004175844926],"iteration":142,"passed_time":1.034326923,"remaining_time":6.198728483},
{"learn":[0.004151735924],"iteration":143,"passed_time":1.04421563,"remaining_time":6.207281802},
{"learn":[0.00411022333],"iteration":144,"passed_time":1.054316787,"remaining_time":6.216833466},
{"learn":[0.00409886083],"iteration":145,"passed_time":1.063659375,"remaining_time":6.221678807},
{"learn":[0.00408320237],"iteration":146,"passed_time":1.072040617,"remaining_time":6.220752694},
{"learn":[0.00403354975],"iteration":147,"passed_time":1.079609125,"remaining_time":6.215047123},
{"learn":[0.004021380022],"iteration":148,"passed_time":1.088003778,"remaining_time":6.214035001},
{"learn":[0.003957316556],"iteration":149,"passed_time":1.095242088,"remaining_time":6.206371833},
{"learn":[0.003906743735],"iteration":150,"passed_time":1.103324344,"remaining_time":6.203459392},
{"learn":[0.003852143869],"iteration":151,"passed_time":1.11078938,"remaining_time":6.197035488},
{"learn":[0.003826113436],"iteration":152,"passed_time":1.118331837,"remaining_time":6.191026574},
{"learn":[0.003783739784],"iteration":153,"passed_time":1.126145346,"remaining_time":6.186486773},
{"learn":[0.003772136371],"iteration":154,"passed_time":1.13405291,"remaining_time":6.182417478},
{"learn":[0.003742863912],"iteration":155,"passed_time":1.161130306,"remaining_time":6.282012683},
{"learn":[0.00372316674],"iteration":156,"passed_time":1.186457163,"remaining_time":6.37059483},
{"learn":[0.003694036624],"iteration":157,"passed_time":1.210669946,"remaining_time":6.451798069},
{"learn":[0.003667468281],"iteration":158,"passed_time":1.234010441,"remaining_time":6.527061516},
{"learn":[0.003622777632],"iteration":159,"passed_time":1.252456384,"remaining_time":6.575396017},
{"learn":[0.003621403124],"iteration":160,"passed_time":1.265793358,"remaining_time":6.596277186},
{"learn":[0.00357565323],"iteration":161,"passed_time":1.298986507,"remaining_time":6.719448721},
{"learn":[0.003575656851],"iteration":162,"passed_time":1.310776717,"remaining_time":6.730798234},
{"learn":[0.003560348254],"iteration":163,"passed_time":1.319580535,"remaining_time":6.726642239},
{"learn":[0.003529014919],"iteration":164,"passed_time":1.329333218,"remaining_time":6.72723174},
{"learn":[0.003529018862],"iteration":165,"passed_time":1.338282079,"remaining_time":6.723658156},
{"learn":[0.003521002671],"iteration":166,"passed_time":1.34749535,"remaining_time":6.721339082},
{"learn":[0.003521008464],"iteration":167,"passed_time":1.354074813,"remaining_time":6.70589431},
{"learn":[0.003510076212],"iteration":168,"passed_time":1.363477404,"remaining_time":6.704436228},
{"learn":[0.003498338341],"iteration":169,"passed_time":1.372574821,"remaining_time":6.701394713},
{"learn":[0.003485905814],"iteration":170,"passed_time":1.381155881,"remaining_time":6.695779097},
{"learn":[0.003447922588],"iteration":171,"passed_time":1.38884148,"remaining_time":6.685818289},
{"learn":[0.003414547126],"iteration":172,"passed_time":1.396828597,"remaining_time":6.677325144},
{"learn":[0.003379251761],"iteration":173,"passed_time":1.404441795,"remaining_time":6.667062772},
{"learn":[0.003356809838],"iteration":174,"passed_time":1.412457804,"remaining_time":6.658729649},
{"learn":[0.003351519488],"iteration":175,"passed_time":1.419256748,"remaining_time":6.644702046},
{"learn":[0.003320550822],"iteration":176,"passed_time":1.427434488,"remaining_time":6.637167141},
{"learn":[0.00330219058],"iteration":177,"passed_time":1.435514981,"remaining_time":6.629175925},
{"learn":[0.003267525902],"iteration":178,"passed_time":1.443890505,"remaining_time":6.622536899},
{"learn":[0.003262347802],"iteration":179,"passed_time":1.450447725,"remaining_time":6.607595193},
{"learn":[0.003257054877],"iteration":180,"passed_time":1.457499759,"remaining_time":6.594985096},
{"learn":[0.003254032924],"iteration":181,"passed_time":1.463879614,"remaining_time":6.579414968},
{"learn":[0.003218256216],"iteration":182,"passed_time":1.470658403,"remaining_time":6.565726311},
{"learn":[0.003196942899],"iteration":183,"passed_time":1.477332969,"remaining_time":6.551650558},
{"learn":[0.003196929702],"iteration":184,"passed_time":1.482918676,"remaining_time":6.532857951},
{"learn":[0.003173191323],"iteration":185,"passed_time":1.490563883,"remaining_time":6.523220434},
{"learn":[0.003156898636],"iteration":186,"passed_time":1.498002684,"remaining_time":6.512706857},
{"learn":[0.003156888738],"iteration":187,"passed_time":1.504798648,"remaining_time":6.499449478},
{"learn":[0.003131789128],"iteration":188,"passed_time":1.511294466,"remaining_time":6.484972548},
{"learn":[0.003131791622],"iteration":189,"passed_time":1.517061851,"remaining_time":6.467474207},
{"learn":[0.003114704823],"iteration":190,"passed_time":1.524101088,"remaining_time":6.455485762},
{"learn":[0.00311469734],"iteration":191,"passed_time":1.52930503,"remaining_time":6.435825334},
{"learn":[0.00310599993],"iteration":192,"passed_time":1.536086489,"remaining_time":6.422910862},
{"learn":[0.003106001539],"iteration":193,"passed_time":1.542219509,"remaining_time":6.407365589},
{"learn":[0.003097534099],"iteration":194,"passed_time":1.548426366,"remaining_time":6.392221664},
{"learn":[0.003097535306],"iteration":195,"passed_time":1.553729553,"remaining_time":6.373462044},
{"learn":[0.003097517202],"iteration":196,"passed_time":1.55922211,"remaining_time":6.355610938},
{"learn":[0.003097515029],"iteration":197,"passed_time":1.564711895,"remaining_time":6.337873434},
{"learn":[0.003078823753],"iteration":198,"passed_time":1.571385638,"remaining_time":6.325024602},
{"learn":[0.003076214908],"iteration":199,"passed_time":1.577461808,"remaining_time":6.309847233},
{"learn":[0.003031609632],"iteration":200,"passed_time":1.584017746,"remaining_time":6.296667556},
{"learn":[0.003031619288],"iteration":201,"passed_time":1.589670378,"remaining_time":6.279984958},
{"learn":[0.003008602762],"iteration":202,"passed_time":1.596925611,"remaining_time":6.269703014},
{"learn":[0.003003547452],"iteration":203,"passed_time":1.604420557,"remaining_time":6.260386094},
{"learn":[0.002994736344],"iteration":204,"passed_time":1.610406749,"remaining_time":6.245235928},
{"learn":[0.002989577153],"iteration":205,"passed_time":1.617246064,"remaining_time":6.233462984},
{"learn":[0.002986133239],"iteration":206,"passed_time":1.62376399,"remaining_time":6.220506494},
{"learn":[0.002986130665],"iteration":207,"passed_time":1.628992126,"remaining_time":6.202700788},
{"learn":[0.0029785411],"iteration":208,"passed_time":1.635847376,"remaining_time":6.191173563},
{"learn":[0.002978540859],"iteration":209,"passed_time":1.641861158,"remaining_time":6.176525309},
{"learn":[0.002963087746],"iteration":210,"passed_time":1.648752077,"remaining_time":6.16523881},
{"learn":[0.002960864652],"iteration":211,"passed_time":1.65483068,"remaining_time":6.150974414},
{"learn":[0.002944575103],"iteration":212,"passed_time":1.660701925,"remaining_time":6.136020727},
{"learn":[0.002903706071],"iteration":213,"passed_time":1.667853229,"remaining_time":6.125853449},
{"learn":[0.002888001182],"iteration":214,"passed_time":1.674064183,"remaining_time":6.112280855},
{"learn":[0.002879948862],"iteration":215,"passed_time":1.680259847,"remaining_time":6.098720926},
{"learn":[0.002870167827],"iteration":216,"passed_time":1.687401803,"remaining_time":6.088643374},
{"learn":[0.002846983531],"iteration":217,"passed_time":1.693735314,"remaining_time":6.075692731},
{"learn":[0.002819168298],"iteration":218,"passed_time":1.700767895,"remaining_time":6.065295553},
{"learn":[0.002819174896],"iteration":219,"passed_time":1.706250658,"remaining_time":6.049434151},
{"learn":[0.002819159849],"iteration":220,"passed_time":1.712116884,"remaining_time":6.035018338},
{"learn":[0.002793898182],"iteration":221,"passed_time":1.718616605,"remaining_time":6.022899633},
{"learn":[0.002777319923],"iteration":222,"passed_time":1.724492509,"remaining_time":6.008657757},
{"learn":[0.002772472052],"iteration":223,"passed_time":1.731464567,"remaining_time":5.998287965},
{"learn":[0.002756096405],"iteration":224,"passed_time":1.737654944,"remaining_time":5.985255919},
{"learn":[0.002732154609],"iteration":225,"passed_time":1.743916663,"remaining_time":5.972528748},
{"learn":[0.002715642171],"iteration":226,"passed_time":1.750409139,"remaining_time":5.960644337},
{"learn":[0.002684952237],"iteration":227,"passed_time":1.756664017,"remaining_time":5.948002725},
{"learn":[0.00268494596],"iteration":228,"passed_time":1.762716049,"remaining_time":5.934733946},
{"learn":[0.002673959394],"iteration":229,"passed_time":1.769442759,"remaining_time":5.923786626},
{"learn":[0.002663513072],"iteration":230,"passed_time":1.775310238,"remaining_time":5.910015466},
{"learn":[0.002663520957],"iteration":231,"passed_time":1.781381889,"remaining_time":5.896988321},
{"learn":[0.002663514922],"iteration":232,"passed_time":1.786615199,"remaining_time":5.88126119},
{"learn":[0.002629638724],"iteration":233,"passed_time":1.792809647,"remaining_time":5.86877004},
{"learn":[0.002608845051],"iteration":234,"passed_time":1.799412044,"remaining_time":5.857660484},
{"learn":[0.002604435555],"iteration":235,"passed_time":1.805548864,"remaining_time":5.845081915},
{"learn":[0.002604435555],"iteration":236,"passed_time":1.811181319,"remaining_time":5.83093395},
{"learn":[0.002578957677],"iteration":237,"passed_time":1.817540982,"remaining_time":5.819185834},
{"learn":[0.00257153886],"iteration":238,"passed_time":1.823377543,"remaining_time":5.805817197},
{"learn":[0.002555577448],"iteration":239,"passed_time":1.830382961,"remaining_time":5.796212711},
{"learn":[0.002544718098],"iteration":240,"passed_time":1.836301928,"remaining_time":5.783208147},
{"learn":[0.002540746332],"iteration":241,"passed_time":1.842027488,"remaining_time":5.769656347},
{"learn":[0.002537189687],"iteration":242,"passed_time":1.848100664,"remaining_time":5.757251862},
{"learn":[0.00253719017],"iteration":243,"passed_time":1.853294062,"remaining_time":5.742173406},
{"learn":[0.002518514021],"iteration":244,"passed_time":1.859842257,"remaining_time":5.731350627},
{"learn":[0.002518514021],"iteration":245,"passed_time":1.864675621,"remaining_time":5.715306578},
{"learn":[0.002518502354],"iteration":246,"passed_time":1.869770929,"remaining_time":5.700151862},
{"learn":[0.002512395764],"iteration":247,"passed_time":1.876124398,"remaining_time":5.688893335},
{"learn":[0.002496042004],"iteration":248,"passed_time":1.882128459,"remaining_time":5.676620372},
{"learn":[0.002496022048],"iteration":249,"passed_time":1.887330427,"remaining_time":5.661991282},
{"learn":[0.002490218733],"iteration":250,"passed_time":1.893962512,"remaining_time":5.651704866},
{"learn":[0.002474257643],"iteration":251,"passed_time":1.899718717,"remaining_time":5.638847621},
{"learn":[0.002464800641],"iteration":252,"passed_time":1.905505948,"remaining_time":5.626138116},
{"learn":[0.002458117115],"iteration":253,"passed_time":1.912159174,"remaining_time":5.61602655},
{"learn":[0.002450022551],"iteration":254,"passed_time":1.917975017,"remaining_time":5.603495637},
{"learn":[0.00243283155],"iteration":255,"passed_time":1.92471115,"remaining_time":5.59369178},
{"learn":[0.002432826158],"iteration":256,"passed_time":1.930198971,"remaining_time":5.580302862},
{"learn":[0.002428941617],"iteration":257,"passed_time":1.936741787,"remaining_time":5.570009326},
{"learn":[0.002408271539],"iteration":258,"passed_time":1.944348767,"remaining_time":5.56278933},
{"learn":[0.002392856004],"iteration":259,"passed_time":1.95111803,"remaining_time":5.553182084},
{"learn":[0.002380160758],"iteration":260,"passed_time":1.95896501,"remaining_time":5.546648054},
{"learn":[0.002380152148],"iteration":261,"passed_time":1.964551526,"remaining_time":5.533736742},
{"learn":[0.002365702115],"iteration":262,"passed_time":1.97176891,"remaining_time":5.525451281},
{"learn":[0.002365679585],"iteration":263,"passed_time":1.980423331,"remaining_time":5.521180196},
{"learn":[0.002365684091],"iteration":264,"passed_time":1.994374978,"remaining_time":5.531568336},
{"learn":[0.002353260898],"iteration":265,"passed_time":2.00325214,"remaining_time":5.527770942},
{"learn":[0.002353260898],"iteration":266,"passed_time":2.01562634,"remaining_time":5.533535982},
{"learn":[0.00234440473],"iteration":267,"passed_time":2.025255623,"remaining_time":5.531668344},
{"learn":[0.002344409316],"iteration":268,"passed_time":2.032911236,"remaining_time":5.524379604},
{"learn":[0.002344395396],"iteration":269,"passed_time":2.042628747,"remaining_time":5.522662908},
{"learn":[0.00234439612],"iteration":270,"passed_time":2.121295145,"remaining_time":5.706362218},
{"learn":[0.0023443892],"iteration":271,"passed_time":2.14099451,"remaining_time":5.730308836},
{"learn":[0.002344390005],"iteration":272,"passed_time":2.151653789,"remaining_time":5.729861922},
{"learn":[0.002344385499],"iteration":273,"passed_time":2.159671673,"remaining_time":5.722341732},
{"learn":[0.002344387671],"iteration":274,"passed_time":2.185433604,"remaining_time":5.761597683},
{"learn":[0.002335960303],"iteration":275,"passed_time":2.197778691,"remaining_time":5.765187581},
{"learn":[0.002317945498],"iteration":276,"passed_time":2.207288549,"remaining_time":5.761262169},
{"learn":[0.00230420372],"iteration":277,"passed_time":2.215232217,"remaining_time":5.753228995},
{"learn":[0.002288797277],"iteration":278,"passed_time":2.224104713,"remaining_time":5.747596768},
{"learn":[0.002274379672],"iteration":279,"passed_time":2.233223605,"remaining_time":5.742574983},
{"learn":[0.002250008675],"iteration":280,"passed_time":2.242844804,"remaining_time":5.738809302},
{"learn":[0.00223675154],"iteration":281,"passed_time":2.258917496,"remaining_time":5.751428234},
{"learn":[0.002228853793],"iteration":282,"passed_time":2.274193966,"remaining_time":5.761827114},
{"learn":[0.002223401709],"iteration":283,"passed_time":2.282513103,"remaining_time":5.754504866},
{"learn":[0.002218612657],"iteration":284,"passed_time":2.291194596,"remaining_time":5.748084687},
{"learn":[0.002218612657],"iteration":285,"passed_time":2.298438006,"remaining_time":5.738058519},
{"learn":[0.002211708657],"iteration":286,"passed_time":2.307037429,"remaining_time":5.731420513},
{"learn":[0.00220431921],"iteration":287,"passed_time":2.316485508,"remaining_time":5.72686695},
{"learn":[0.002204330073],"iteration":288,"passed_time":2.322874508,"remaining_time":5.714753546},
{"learn":[0.002181616016],"iteration":289,"passed_time":2.330411904,"remaining_time":5.705491214},
{"learn":[0.002181612556],"iteration":290,"passed_time":2.337393369,"remaining_time":5.694886249},
{"learn":[0.002172995692],"iteration":291,"passed_time":2.343889563,"remaining_time":5.683129489},
{"learn":[0.002165086681],"iteration":292,"passed_time":2.351891404,"remaining_time":5.675041715},
{"learn":[0.002165075335],"iteration":293,"passed_time":2.360461803,"remaining_time":5.668319841},
{"learn":[0.002158857623],"iteration":294,"passed_time":2.369769714,"remaining_time":5.66334796},
{"learn":[0.002152865455],"iteration":295,"passed_time":2.379849994,"remaining_time":5.660183769},
{"learn":[0.00214799264],"iteration":296,"passed_time":2.386640719,"remaining_time":5.649186618},
{"learn":[0.00214799264],"iteration":297,"passed_time":2.392196456,"remaining_time":5.63530843},
{"learn":[0.002147981375],"iteration":298,"passed_time":2.398572972,"remaining_time":5.623410213},
{"learn":[0.002133487891],"iteration":299,"passed_time":2.404970019,"remaining_time":5.611596712},
{"learn":[0.002133490868],"iteration":300,"passed_time":2.411537531,"remaining_time":5.600215064},
{"learn":[0.002121482795],"iteration":301,"passed_time":2.41945565,"remaining_time":5.591986899},
{"learn":[0.002121478852],"iteration":302,"passed_time":2.427092971,"remaining_time":5.583114853},
{"learn":[0.002121476116],"iteration":303,"passed_time":2.433498264,"remaining_time":5.571430235},
{"learn":[0.002121479094],"iteration":304,"passed_time":2.439527192,"remaining_time":5.558922619},
{"learn":[0.002121458495],"iteration":305,"passed_time":2.446618222,"remaining_time":5.548866164},
{"learn":[0.002121450126],"iteration":306,"passed_time":2.452254603,"remaining_time":5.535545407},
{"learn":[0.00212145246],"iteration":307,"passed_time":2.457754334,"remaining_time":5.521967531},
{"learn":[0.002114768452],"iteration":308,"passed_time":2.465570319,"remaining_time":5.513621653},
{"learn":[0.002109815814],"iteration":309,"passed_time":2.472077324,"remaining_time":5.502365656},
{"learn":[0.002099760875],"iteration":310,"passed_time":2.479058088,"remaining_time":5.492189784},
{"learn":[0.002076615122],"iteration":311,"passed_time":2.485635802,"remaining_time":5.481145614},
{"learn":[0.002076615444],"iteration":312,"passed_time":2.491730514,"remaining_time":5.46906985},
{"learn":[0.002076606512],"iteration":313,"passed_time":2.497596262,"remaining_time":5.456531961},
{"learn":[0.00207660265],"iteration":314,"passed_time":2.503127033,"remaining_time":5.443307992},
{"learn":[0.00207660265],"iteration":315,"passed_time":2.509161133,"remaining_time":5.431222199},
{"learn":[0.002073516485],"iteration":316,"passed_time":2.515444524,"remaining_time":5.419711704},
{"learn":[0.002073517451],"iteration":317,"passed_time":2.520855177,"remaining_time":5.40636236},
{"learn":[0.002073513267],"iteration":318,"passed_time":2.526516366,"remaining_time":5.393597635},
{"learn":[0.002073518497],"iteration":319,"passed_time":2.53192896,"remaining_time":5.380349041},
{"learn":[0.002066460003],"iteration":320,"passed_time":2.537961561,"remaining_time":5.368460748},
{"learn":[0.002066454773],"iteration":321,"passed_time":2.544357061,"remaining_time":5.357372942},
{"learn":[0.002066454773],"iteration":322,"passed_time":2.549642188,"remaining_time":5.343986878},
{"learn":[0.002066450187],"iteration":323,"passed_time":2.55509157,"remaining_time":5.330993524},
{"learn":[0.002066460325],"iteration":324,"passed_time":2.562395199,"remaining_time":5.321897721},
{"learn":[0.002054146082],"iteration":325,"passed_time":2.568673247,"remaining_time":5.310692542},
{"learn":[0.002049969211],"iteration":326,"passed_time":2.576262156,"remaining_time":5.302215385},
{"learn":[0.002049973234],"iteration":327,"passed_time":2.581784198,"remaining_time":5.289509089},
{"learn":[0.002049973234],"iteration":328,"passed_time":2.586952459,"remaining_time":5.276124923},
{"learn":[0.002049963176],"iteration":329,"passed_time":2.593127363,"remaining_time":5.264834343},
{"learn":[0.0020426587],"iteration":330,"passed_time":2.598942662,"remaining_time":5.252847858},
{"learn":[0.002042643412],"iteration":331,"passed_time":2.606280931,"remaining_time":5.243962837},
{"learn":[0.002036909215],"iteration":332,"passed_time":2.61257924,"remaining_time":5.233004063},
{"learn":[0.002036909215],"iteration":333,"passed_time":2.619266256,"remaining_time":5.222848283},
{"learn":[0.002033129521],"iteration":334,"passed_time":2.62741551,"remaining_time":5.215615863},
{"learn":[0.002015410023],"iteration":335,"passed_time":2.634137887,"remaining_time":5.205558204},
{"learn":[0.002015400046],"iteration":336,"passed_time":2.639392155,"remaining_time":5.192632043},
{"learn":[0.002015394976],"iteration":337,"passed_time":2.644681306,"remaining_time":5.1798196},
{"learn":[0.002015391194],"iteration":338,"passed_time":2.651017572,"remaining_time":5.16909326},
{"learn":[0.002003025695],"iteration":339,"passed_time":2.656895572,"remaining_time":5.157503169},
{"learn":[0.001992142124],"iteration":340,"passed_time":2.662624491,"remaining_time":5.145658474},
{"learn":[0.001992136572],"iteration":341,"passed_time":2.668957826,"remaining_time":5.135012426},
{"learn":[0.00199213279],"iteration":342,"passed_time":2.67427382,"remaining_time":5.122442856},
{"learn":[0.001987841497],"iteration":343,"passed_time":2.680995925,"remaining_time":5.112596881},
{"learn":[0.001987843428],"iteration":344,"passed_time":2.686762278,"remaining_time":5.10095447},
{"learn":[0.001987838681],"iteration":345,"passed_time":2.69240326,"remaining_time":5.089109053},
{"learn":[0.001978293569],"iteration":346,"passed_time":2.698839613,"remaining_time":5.07879616},
{"learn":[0.001962763693],"iteration":347,"passed_time":2.704975681,"remaining_time":5.067942943},
{"learn":[0.001962768521],"iteration":348,"passed_time":2.710245943,"remaining_time":5.055501745},
{"learn":[0.001950626151],"iteration":349,"passed_time":2.716229018,"remaining_time":5.044425319},
{"learn":[0.001929999363],"iteration":350,"passed_time":2.722171489,"remaining_time":5.033302838},
{"learn":[0.001923799273],"iteration":351,"passed_time":2.72800896,"remaining_time":5.022016495},
{"learn":[0.001923799273],"iteration":352,"passed_time":2.733755745,"remaining_time":5.010594808},
{"learn":[0.001915343822],"iteration":353,"passed_time":2.739474245,"remaining_time":4.999153566},
{"learn":[0.001915343018],"iteration":354,"passed_time":2.744416818,"remaining_time":4.986334783},
{"learn":[0.001915335856],"iteration":355,"passed_time":2.750252108,"remaining_time":4.975175162},
{"learn":[0.001915332075],"iteration":356,"passed_time":2.75562926,"remaining_time":4.963220207},
{"learn":[0.001915332075],"iteration":357,"passed_time":2.760835802,"remaining_time":4.950996046},
{"learn":[0.001915342776],"iteration":358,"passed_time":2.766561051,"remaining_time":4.939737141},
{"learn":[0.001915335535],"iteration":359,"passed_time":2.771775745,"remaining_time":4.927601325},
{"learn":[0.001904306322],"iteration":360,"passed_time":2.777800653,"remaining_time":4.916937998},
{"learn":[0.001904305195],"iteration":361,"passed_time":2.783379796,"remaining_time":4.905514668},
{"learn":[0.001904298597],"iteration":362,"passed_time":2.788628938,"remaining_time":4.893544445},
{"learn":[0.001904298597],"iteration":363,"passed_time":2.79399664,"remaining_time":4.881818304},
{"learn":[0.001894873459],"iteration":364,"passed_time":2.800065743,"remaining_time":4.871347252},
{"learn":[0.001888200636],"iteration":365,"passed_time":2.806049657,"remaining_time":4.860752684},
{"learn":[0.001888213188],"iteration":366,"passed_time":2.811165682,"remaining_time":4.848686312},
{"learn":[0.001880679628],"iteration":367,"passed_time":2.816884002,"remaining_time":4.837692091},
{"learn":[0.001880671984],"iteration":368,"passed_time":2.822038236,"remaining_time":4.825761862},
{"learn":[0.001880664581],"iteration":369,"passed_time":2.82792391,"remaining_time":4.815113684},
{"learn":[0.001868576686],"iteration":370,"passed_time":2.833803993,"remaining_time":4.804481703},
{"learn":[0.001868576284],"iteration":371,"passed_time":2.838829795,"remaining_time":4.792433095},
{"learn":[0.001868564697],"iteration":372,"passed_time":2.84465339,"remaining_time":4.781763206},
{"learn":[0.001868556007],"iteration":373,"passed_time":2.849753393,"remaining_time":4.769908086},
{"learn":[0.001868556007],"iteration":374,"passed_time":2.854892441,"remaining_time":4.758154068},
{"learn":[0.001868564697],"iteration":375,"passed_time":2.860627837,"remaining_time":4.747424921},
{"learn":[0.001868564697],"iteration":376,"passed_time":2.866630753,"remaining_time":4.737164348},
{"learn":[0.001868551662],"iteration":377,"passed_time":2.871748865,"remaining_time":4.725470355},
{"learn":[0.001858542829],"iteration":378,"passed_time":2.880437213,"remaining_time":4.719660974},
{"learn":[0.001844847158],"iteration":379,"passed_time":2.886607533,"remaining_time":4.70972808},
{"learn":[0.001844852066],"iteration":380,"passed_time":2.89263266,"remaining_time":4.699579046},
{"learn":[0.001844835973],"iteration":381,"passed_time":2.897851888,"remaining_time":4.688147818},
{"learn":[0.001844841284],"iteration":382,"passed_time":2.903183303,"remaining_time":4.67692976},
{"learn":[0.001844827685],"iteration":383,"passed_time":2.908556072,"remaining_time":4.665808699},
{"learn":[0.001834915894],"iteration":384,"passed_time":2.914351872,"remaining_time":4.65539325},
{"learn":[0.001834915894],"iteration":385,"passed_time":2.91932772,"remaining_time":4.643697462},
{"learn":[0.001834915572],"iteration":386,"passed_time":2.925014393,"remaining_time":4.633162332},
{"learn":[0.001834905111],"iteration":387,"passed_time":2.930214946,"remaining_time":4.62188543},
{"learn":[0.001834907123],"iteration":388,"passed_time":2.935487863,"remaining_time":4.61075343},
{"learn":[0.001834905111],"iteration":389,"passed_time":2.941329993,"remaining_time":4.600541784},
{"learn":[0.001834904387],"iteration":390,"passed_time":2.946251082,"remaining_time":4.588917926},
{"learn":[0.001825295869],"iteration":391,"passed_time":2.952209875,"remaining_time":4.578937765},
{"learn":[0.001819528441],"iteration":392,"passed_time":2.959014389,"remaining_time":4.57028431},
{"learn":[0.001819514279],"iteration":393,"passed_time":2.964030506,"remaining_time":4.558889561},
{"learn":[0.001819516934],"iteration":394,"passed_time":2.968921427,"remaining_time":4.54733535},
{"learn":[0.001819513394],"iteration":395,"passed_time":2.974620045,"remaining_time":4.537046735},
{"learn":[0.001809304363],"iteration":396,"passed_time":2.980503467,"remaining_time":4.527061941},
{"learn":[0.001809299938],"iteration":397,"passed_time":2.985389389,"remaining_time":4.515588975},
{"learn":[0.001801758974],"iteration":398,"passed_time":2.992061777,"remaining_time":4.50683992},
{"learn":[0.001801742962],"iteration":399,"passed_time":2.997125417,"remaining_time":4.495688126},
{"learn":[0.001796433864],"iteration":400,"passed_time":3.002542415,"remaining_time":4.48509453},
{"learn":[0.001796434346],"iteration":401,"passed_time":3.007569544,"remaining_time":4.473946734},
{"learn":[0.001796425817],"iteration":402,"passed_time":3.012819383,"remaining_time":4.463159236},
{"learn":[0.001796425817],"iteration":403,"passed_time":3.017650133,"remaining_time":4.45178089},
{"learn":[0.001796425495],"iteration":404,"passed_time":3.023622836,"remaining_time":4.442112561},
{"learn":[0.00179642292],"iteration":405,"passed_time":3.02872417,"remaining_time":4.431187578},
{"learn":[0.001796421955],"iteration":406,"passed_time":3.033926498,"remaining_time":4.420438362},
{"learn":[0.001796421955],"iteration":407,"passed_time":3.040188836,"remaining_time":4.41125439},
{"learn":[0.00179641761],"iteration":408,"passed_time":3.045394093,"remaining_time":4.400557234},
{"learn":[0.00179641423],"iteration":409,"passed_time":3.050399338,"remaining_time":4.389599047},
{"learn":[0.001796416],"iteration":410,"passed_time":3.056237239,"remaining_time":4.379863099},
{"learn":[0.001786965838],"iteration":411,"passed_time":3.061834585,"remaining_time":4.369802757},
{"learn":[0.001786935985],"iteration":412,"passed_time":3.067114683,"remaining_time":4.359313121},
{"learn":[0.001786929468],"iteration":413,"passed_time":3.073340277,"remaining_time":4.350186962},
{"learn":[0.0017869281],"iteration":414,"passed_time":3.080449064,"remaining_time":4.342319765},
{"learn":[0.001774776316],"iteration":415,"passed_time":3.08984503,"remaining_time":4.337667061},
{"learn":[0.001774776316],"iteration":416,"passed_time":3.098630827,"remaining_time":4.332138542},
{"learn":[0.001772843701],"iteration":417,"passed_time":3.10527863,"remaining_time":4.323617614},
{"learn":[0.001772844023],"iteration":418,"passed_time":3.111196218,"remaining_time":4.314093086},
{"learn":[0.001772835976],"iteration":419,"passed_time":3.116786553,"remaining_time":4.304133811},
{"learn":[0.001772826642],"iteration":420,"passed_time":3.122985374,"remaining_time":4.295032142},
{"learn":[0.001772821251],"iteration":421,"passed_time":3.128589693,"remaining_time":4.285129959},
{"learn":[0.001762821511],"iteration":422,"passed_time":3.137293289,"remaining_time":4.279475716},
{"learn":[0.001762822557],"iteration":423,"passed_time":3.142897146,"remaining_time":4.269596123},
{"learn":[0.001762814913],"iteration":424,"passed_time":3.149017742,"remaining_time":4.260435769},
{"learn":[0.001762826178],"iteration":425,"passed_time":3.156109507,"remaining_time":4.252598255},
{"learn":[0.001762814269],"iteration":426,"passed_time":3.159191835,"remaining_time":4.239383891},
{"learn":[0.001762808958],"iteration":427,"passed_time":3.164954623,"remaining_time":4.229799169},
{"learn":[0.001762817166],"iteration":428,"passed_time":3.170869502,"remaining_time":4.220434698},
{"learn":[0.00176280928],"iteration":429,"passed_time":3.176443232,"remaining_time":4.210634052},
{"learn":[0.001762815637],"iteration":430,"passed_time":3.182279412,"remaining_time":4.201199502},
{"learn":[0.001762818212],"iteration":431,"passed_time":3.188450089,"remaining_time":4.192221413},
{"learn":[0.001762818212],"iteration":432,"passed_time":3.194531236,"remaining_time":4.183139054},
{"learn":[0.001762818212],"iteration":433,"passed_time":3.201253743,"remaining_time":4.174906955},
{"learn":[0.001762817649],"iteration":434,"passed_time":3.207685496,"remaining_time":4.16630415},
{"learn":[0.00176281266],"iteration":435,"passed_time":3.215570699,"remaining_time":4.159591455},
{"learn":[0.001762810487],"iteration":436,"passed_time":3.222120691,"remaining_time":4.151153202},
{"learn":[0.001762808958],"iteration":437,"passed_time":3.233286714,"remaining_time":4.148646424},
{"learn":[0.001762807591],"iteration":438,"passed_time":3.241726174,"remaining_time":4.142615909},
{"learn":[0.001762804452],"iteration":439,"passed_time":3.249539665,"remaining_time":4.135777755},
{"learn":[0.001762804855],"iteration":440,"passed_time":3.257173307,"remaining_time":4.128707208},
{"learn":[0.001762805418],"iteration":441,"passed_time":3.26510077,"remaining_time":4.122005044},
{"learn":[0.001762803245],"iteration":442,"passed_time":3.273492361,"remaining_time":4.115880914},
{"learn":[0.001762805418],"iteration":443,"passed_time":3.282196538,"remaining_time":4.110138007},
{"learn":[0.001762803567],"iteration":444,"passed_time":3.288393112,"remaining_time":4.101254331},
{"learn":[0.001762789888],"iteration":445,"passed_time":3.294537968,"remaining_time":4.092318463},
{"learn":[0.001762796969],"iteration":446,"passed_time":3.30061569,"remaining_time":4.083312028},
{"learn":[0.001762792141],"iteration":447,"passed_time":3.306028149,"remaining_time":4.07349897},
{"learn":[0.001762793026],"iteration":448,"passed_time":3.311907235,"remaining_time":4.064278144},
{"learn":[0.00176279021],"iteration":449,"passed_time":3.317462313,"remaining_time":4.05467616},
{"learn":[0.001762780474],"iteration":450,"passed_time":3.32324673,"remaining_time":4.045371297},
{"learn":[0.00176279013],"iteration":451,"passed_time":3.329350869,"remaining_time":4.036469637},
{"learn":[0.001754057154],"iteration":452,"passed_time":3.335382617,"remaining_time":4.027492917},
{"learn":[0.001754057154],"iteration":453,"passed_time":3.340492262,"remaining_time":4.017420209},
{"learn":[0.001754049671],"iteration":454,"passed_time":3.346272797,"remaining_time":4.00817291},
{"learn":[0.001754054901],"iteration":455,"passed_time":3.351497271,"remaining_time":3.998277446},
{"learn":[0.0017540409],"iteration":456,"passed_time":3.356693304,"remaining_time":3.98836863},
{"learn":[0.001754046935],"iteration":457,"passed_time":3.362785556,"remaining_time":3.979540986},
{"learn":[0.001754045084],"iteration":458,"passed_time":3.367970633,"remaining_time":3.969656018},
{"learn":[0.001754042107],"iteration":459,"passed_time":3.373330878,"remaining_time":3.959997118},
{"learn":[0.001754046452],"iteration":460,"passed_time":3.379364319,"remaining_time":3.951143966},
{"learn":[0.001754046452],"iteration":461,"passed_time":3.384293866,"remaining_time":3.941017532},
{"learn":[0.001754041463],"iteration":462,"passed_time":3.389862445,"remaining_time":3.931654715},
{"learn":[0.001754040015],"iteration":463,"passed_time":3.395260436,"remaining_time":3.922111193},
{"learn":[0.001754042992],"iteration":464,"passed_time":3.400946713,"remaining_time":3.912917186},
{"learn":[0.001754037279],"iteration":465,"passed_time":3.406521913,"remaining_time":3.903610947},
{"learn":[0.001754039773],"iteration":466,"passed_time":3.411971677,"remaining_time":3.894177525},
{"learn":[0.001754035831],"iteration":467,"passed_time":3.417787194,"remaining_time":3.885176895},
{"learn":[0.001754039371],"iteration":468,"passed_time":3.423362455,"remaining_time":3.875917833},
{"learn":[0.001754037199],"iteration":469,"passed_time":3.429320607,"remaining_time":3.867106216},
{"learn":[0.001754032049],"iteration":470,"passed_time":3.434848031,"remaining_time":3.857822947},
{"learn":[0.001754026658],"iteration":471,"passed_time":3.4406673,"remaining_time":3.848882065},
{"learn":[0.001754022554],"iteration":472,"passed_time":3.446590813,"remaining_time":3.840070525},
{"learn":[0.001754025048],"iteration":473,"passed_time":3.452458647,"remaining_time":3.831209385},
{"learn":[0.001754026255],"iteration":474,"passed_time":3.45911278,"remaining_time":3.823229914},
{"learn":[0.001754022473],"iteration":475,"passed_time":3.464964514,"remaining_time":3.8143727},
{"learn":[0.001754024887],"iteration":476,"passed_time":3.470804004,"remaining_time":3.805514663},
{"learn":[0.001754020623],"iteration":477,"passed_time":3.476829836,"remaining_time":3.79687275},
{"learn":[0.001749215478],"iteration":478,"passed_time":3.483432754,"remaining_time":3.788869447},
{"learn":[0.001749218134],"iteration":479,"passed_time":3.487159147,"remaining_time":3.777755743},
{"learn":[0.001749215639],"iteration":480,"passed_time":3.492864056,"remaining_time":3.768807578},
{"learn":[0.00174921403],"iteration":481,"passed_time":3.49787917,"remaining_time":3.759131556},
{"learn":[0.001749219824],"iteration":482,"passed_time":3.5029867,"remaining_time":3.749573755},
{"learn":[0.001749221433],"iteration":483,"passed_time":3.508948361,"remaining_time":3.740944947},
{"learn":[0.001749229962],"iteration":484,"passed_time":3.514240087,"remaining_time":3.731615763},
{"learn":[0.001749205823],"iteration":485,"passed_time":3.519321888,"remaining_time":3.722081173},
{"learn":[0.001749209765],"iteration":486,"passed_time":3.525291198,"remaining_time":3.713499763},
{"learn":[0.001749211938],"iteration":487,"passed_time":3.530266847,"remaining_time":3.703886528},
{"learn":[0.001749211053],"iteration":488,"passed_time":3.535527764,"remaining_time":3.694590363},
{"learn":[0.001749210409],"iteration":489,"passed_time":3.54116924,"remaining_time":3.68570676},
{"learn":[0.001749213225],"iteration":490,"passed_time":3.546333919,"remaining_time":3.676342087},
{"learn":[0.001749219421],"iteration":491,"passed_time":3.551658154,"remaining_time":3.667159232},
{"learn":[0.001749211858],"iteration":492,"passed_time":3.557234318,"remaining_time":3.658251114},
{"learn":[0.00174920711],"iteration":493,"passed_time":3.562147082,"remaining_time":3.648676971},
{"learn":[0.001739253557],"iteration":494,"passed_time":3.568237537,"remaining_time":3.640323144},
{"learn":[0.001739250901],"iteration":495,"passed_time":3.574427294,"remaining_time":3.632079347},
{"learn":[0.001739253074],"iteration":496,"passed_time":3.580146078,"remaining_time":3.623367157},
{"learn":[0.001739252269],"iteration":497,"passed_time":3.585719837,"remaining_time":3.6145208},
{"learn":[0.001739250821],"iteration":498,"passed_time":3.590875747,"remaining_time":3.605268034},
{"learn":[0.001739244384],"iteration":499,"passed_time":3.595851008,"remaining_time":3.595851008},
{"learn":[0.001739238751],"iteration":500,"passed_time":3.601708296,"remaining_time":3.587330219},
{"learn":[0.001739238751],"iteration":501,"passed_time":3.60738091,"remaining_time":3.578636839},
{"learn":[0.001739244384],"iteration":502,"passed_time":3.613135044,"remaining_time":3.570036018},
{"learn":[0.001739237786],"iteration":503,"passed_time":3.618840505,"remaining_time":3.561398592},
{"learn":[0.001739243901],"iteration":504,"passed_time":3.623955267,"remaining_time":3.552193776},
{"learn":[0.001739234808],"iteration":505,"passed_time":3.629350284,"remaining_time":3.543278735},
{"learn":[0.001739241407],"iteration":506,"passed_time":3.635265715,"remaining_time":3.534883625},
{"learn":[0.001739242292],"iteration":507,"passed_time":3.640747318,"remaining_time":3.526078111},
{"learn":[0.001739232314],"iteration":508,"passed_time":3.646162263,"remaining_time":3.517221358},
{"learn":[0.001739237061],"iteration":509,"passed_time":3.649737972,"remaining_time":3.506610992},
{"learn":[0.001739237061],"iteration":510,"passed_time":3.655093536,"remaining_time":3.497731388},
{"learn":[0.001739224267],"iteration":511,"passed_time":3.661019588,"remaining_time":3.489409295},
{"learn":[0.00173923159],"iteration":512,"passed_time":3.667538314,"remaining_time":3.48165918},
{"learn":[0.001738596719],"iteration":513,"passed_time":3.673665025,"remaining_time":3.473543195},
{"learn":[0.001738600662],"iteration":514,"passed_time":3.678730545,"remaining_time":3.464435561},
{"learn":[0.001738593661],"iteration":515,"passed_time":3.68400325,"remaining_time":3.455537932},
{"learn":[0.001738597604],"iteration":516,"passed_time":3.689027246,"remaining_time":3.446421973},
{"learn":[0.001738584247],"iteration":517,"passed_time":3.694078519,"remaining_time":3.437347193},
{"learn":[0.001738598731],"iteration":518,"passed_time":3.700394492,"remaining_time":3.42946002},
{"learn":[0.001738586017],"iteration":519,"passed_time":3.706434461,"remaining_time":3.421324117},
{"learn":[0.001738588351],"iteration":520,"passed_time":3.711726963,"remaining_time":3.412509051},
{"learn":[0.001738591408],"iteration":521,"passed_time":3.717962043,"remaining_time":3.404570606},
{"learn":[0.001738587063],"iteration":522,"passed_time":3.723163246,"remaining_time":3.395695733},
{"learn":[0.001738588029],"iteration":523,"passed_time":3.728435735,"remaining_time":3.386899637},
{"learn":[0.001738594546],"iteration":524,"passed_time":3.734226849,"remaining_time":3.378586197},
{"learn":[0.001738586419],"iteration":525,"passed_time":3.739459803,"remaining_time":3.369779366},
{"learn":[0.001738582316],"iteration":526,"passed_time":3.744655584,"remaining_time":3.360952735},
{"learn":[0.001738581913],"iteration":527,"passed_time":3.750605786,"remaining_time":3.352814263},
{"learn":[0.001738570326],"iteration":528,"passed_time":3.755791861,"remaining_time":3.344003717},
{"learn":[0.001738583603],"iteration":529,"passed_time":3.760631494,"remaining_time":3.334899627},
{"learn":[0.001738580626],"iteration":530,"passed_time":3.766419903,"remaining_time":3.326649594},
{"learn":[0.001738580465],"iteration":531,"passed_time":3.771472286,"remaining_time":3.317761334},
{"learn":[0.001738581913],"iteration":532,"passed_time":3.776391591,"remaining_time":3.308770869},
{"learn":[0.001738582477],"iteration":533,"passed_time":3.781849109,"remaining_time":3.300265328},
{"learn":[0.001738567993],"iteration":534,"passed_time":3.787051192,"remaining_time":3.291549167},
{"learn":[0.001738565177],"iteration":535,"passed_time":3.791902672,"remaining_time":3.282542611},
{"learn":[0.001738568395],"iteration":536,"passed_time":3.798725731,"remaining_time":3.275251422},
{"learn":[0.001738556647],"iteration":537,"passed_time":3.803954391,"remaining_time":3.266592804},
{"learn":[0.00173855021],"iteration":538,"passed_time":3.80893646,"remaining_time":3.257736008},
{"learn":[0.001738551176],"iteration":539,"passed_time":3.814722934,"remaining_time":3.249578795},
{"learn":[0.001738550612],"iteration":540,"passed_time":3.819723594,"remaining_time":3.240763641},
{"learn":[0.001738550612],"iteration":541,"passed_time":3.824569889,"remaining_time":3.231832121},
{"learn":[0.001738549486],"iteration":542,"passed_time":3.841825993,"remaining_time":3.233359998},
{"learn":[0.001738552061],"iteration":543,"passed_time":3.847267553,"remaining_time":3.224915449},
{"learn":[0.0017385519],"iteration":544,"passed_time":3.852192915,"remaining_time":3.216050966},
{"learn":[0.001738558417],"iteration":545,"passed_time":3.857008572,"remaining_time":3.207109692},
{"learn":[0.001738544497],"iteration":546,"passed_time":3.863083601,"remaining_time":3.199226456},
{"learn":[0.00173854329],"iteration":547,"passed_time":3.868185973,"remaining_time":3.190547554},
{"learn":[0.001738535887],"iteration":548,"passed_time":3.873199241,"remaining_time":3.181808484},
{"learn":[0.001738547635],"iteration":549,"passed_time":3.878196014,"remaining_time":3.173069466},
{"learn":[0.001738542163],"iteration":550,"passed_time":3.883425353,"remaining_time":3.164533545},
{"learn":[0.001738542163],"iteration":551,"passed_time":3.888210377,"remaining_time":3.155649002},
{"learn":[0.001738536692],"iteration":552,"passed_time":3.893963192,"remaining_time":3.147561568},
{"learn":[0.001738530657],"iteration":553,"passed_time":3.899215095,"remaining_time":3.1390793},
{"learn":[0.001738532186],"iteration":554,"passed_time":3.905244196,"remaining_time":3.131231833},
{"learn":[0.001738530496],"iteration":555,"passed_time":3.910121569,"remaining_time":3.122471181},
{"learn":[0.001738533473],"iteration":556,"passed_time":3.91541237,"remaining_time":3.114053285},
{"learn":[0.001736857784],"iteration":557,"passed_time":3.921669589,"remaining_time":3.106412112},
{"learn":[0.001736852071],"iteration":558,"passed_time":3.926639302,"remaining_time":3.097760165},
{"learn":[0.001736844185],"iteration":559,"passed_time":3.932425528,"remaining_time":3.089762915},
{"learn":[0.001736830909],"iteration":560,"passed_time":3.937444325,"remaining_time":3.08117301},
{"learn":[0.001736835012],"iteration":561,"passed_time":3.942489294,"remaining_time":3.072616212},
{"learn":[0.001736832196],"iteration":562,"passed_time":3.947312191,"remaining_time":3.063899516},
{"learn":[0.001736837265],"iteration":563,"passed_time":3.95310117,"remaining_time":3.055943458},
{"learn":[0.00173682761],"iteration":564,"passed_time":3.957896089,"remaining_time":3.047229732},
{"learn":[0.00173682761],"iteration":565,"passed_time":3.962700145,"remaining_time":3.038536861},
{"learn":[0.001736837185],"iteration":566,"passed_time":3.967535036,"remaining_time":3.029881253},
{"learn":[0.001736829219],"iteration":567,"passed_time":3.972655824,"remaining_time":3.021456543},
{"learn":[0.001736829058],"iteration":568,"passed_time":3.977681709,"remaining_time":3.012971558},
{"learn":[0.00173682423],"iteration":569,"passed_time":3.983678095,"remaining_time":3.005230843},
{"learn":[0.001736822782],"iteration":570,"passed_time":3.988744691,"remaining_time":2.996797675},
{"learn":[0.001736826322],"iteration":571,"passed_time":3.993621669,"remaining_time":2.988234395},
{"learn":[0.001736819322],"iteration":572,"passed_time":3.999490557,"remaining_time":2.980423155},
{"learn":[0.001736818115],"iteration":573,"passed_time":4.004439051,"remaining_time":2.971935602},
{"learn":[0.001736811758],"iteration":574,"passed_time":4.009508298,"remaining_time":2.963549611},
{"learn":[0.00173681216],"iteration":575,"passed_time":4.015364073,"remaining_time":2.955754109},
{"learn":[0.001736824552],"iteration":576,"passed_time":4.020390522,"remaining_time":2.94735735},
{"learn":[0.001736819644],"iteration":577,"passed_time":4.025354475,"remaining_time":2.938926624},
{"learn":[0.001736815942],"iteration":578,"passed_time":4.031129197,"remaining_time":2.931097395},
{"learn":[0.001736816023],"iteration":579,"passed_time":4.034266922,"remaining_time":2.921365702},
{"learn":[0.001736812965],"iteration":580,"passed_time":4.039198954,"remaining_time":2.912950709},
{"learn":[0.001736805884],"iteration":581,"passed_time":4.04605627,"remaining_time":2.905930448},
{"learn":[0.00173680347],"iteration":582,"passed_time":4.053490741,"remaining_time":2.899323566},
{"learn":[0.001736789067],"iteration":583,"passed_time":4.06113092,"remaining_time":2.892860382},
{"learn":[0.001736802183],"iteration":584,"passed_time":4.067083957,"remaining_time":2.885196311},
{"learn":[0.001736809585],"iteration":585,"passed_time":4.072308159,"remaining_time":2.87702317},
{"learn":[0.00173679655],"iteration":586,"passed_time":4.079200795,"remaining_time":2.87003395},
{"learn":[0.001736798723],"iteration":587,"passed_time":4.084462776,"remaining_time":2.861902489},
{"learn":[0.001736799527],"iteration":588,"passed_time":4.090191289,"remaining_time":2.854106316},
{"learn":[0.001736791963],"iteration":589,"passed_time":4.096841726,"remaining_time":2.84695781},
{"learn":[0.001736787055],"iteration":590,"passed_time":4.101706154,"remaining_time":2.838574986},
{"learn":[0.001736782871],"iteration":591,"passed_time":4.10723713,"remaining_time":2.830663427},
{"learn":[0.001736779733],"iteration":592,"passed_time":4.114486492,"remaining_time":2.823939295},
{"learn":[0.001736785365],"iteration":593,"passed_time":4.13817279,"remaining_time":2.828448069},
{"learn":[0.001736777077],"iteration":594,"passed_time":4.160395065,"remaining_time":2.831865549},
{"learn":[0.00173678279],"iteration":595,"passed_time":4.179319019,"remaining_time":2.832961214},
{"learn":[0.001736773135],"iteration":596,"passed_time":4.201340917,"remaining_time":2.836081054},
{"learn":[0.001736774342],"iteration":597,"passed_time":4.215597265,"remaining_time":2.833896489},
{"learn":[0.001736761467],"iteration":598,"passed_time":4.221964797,"remaining_time":2.826390456},
{"learn":[0.001736764927],"iteration":599,"passed_time":4.250070415,"remaining_time":2.833380277},
{"learn":[0.001736760823],"iteration":600,"passed_time":4.259158858,"remaining_time":2.827627927},
{"learn":[0.001736766054],"iteration":601,"passed_time":4.266292406,"remaining_time":2.820572056},
{"learn":[0.001736767422],"iteration":602,"passed_time":4.273224457,"remaining_time":2.813383266},
{"learn":[0.00173677233],"iteration":603,"passed_time":4.279267103,"remaining_time":2.805612207},
{"learn":[0.001736772813],"iteration":604,"passed_time":4.286142277,"remaining_time":2.798390412},
{"learn":[0.00173674119],"iteration":605,"passed_time":4.29401922,"remaining_time":2.791821077},
{"learn":[0.001736740305],"iteration":606,"passed_time":4.300248226,"remaining_time":2.784180483},
{"learn":[0.001736741029],"iteration":607,"passed_time":4.307125898,"remaining_time":2.77696275},
{"learn":[0.001736742236],"iteration":608,"passed_time":4.313563354,"remaining_time":2.7694635},
{"learn":[0.001736753421],"iteration":609,"passed_time":4.319680842,"remaining_time":2.761763161},
{"learn":[0.001736739098],"iteration":610,"passed_time":4.326976307,"remaining_time":2.754817976},
{"learn":[0.001736739581],"iteration":611,"passed_time":4.333063684,"remaining_time":2.747105735},
{"learn":[0.001736733385],"iteration":612,"passed_time":4.339687915,"remaining_time":2.739737721},
{"learn":[0.001736727913],"iteration":613,"passed_time":4.344317902,"remaining_time":2.731118421},
{"learn":[0.001736735477],"iteration":614,"passed_time":4.350414669,"remaining_time":2.723430321},
{"learn":[0.00173673942],"iteration":615,"passed_time":4.356766266,"remaining_time":2.715906244},
{"learn":[0.001736721878],"iteration":616,"passed_time":4.363024007,"remaining_time":2.708327706},
{"learn":[0.001736721878],"iteration":617,"passed_time":4.369004274,"remaining_time":2.70058193},
{"learn":[0.001736732097],"iteration":618,"passed_time":4.375913599,"remaining_time":2.693413702},
{"learn":[0.001736734753],"iteration":619,"passed_time":4.382005656,"remaining_time":2.685745402},
{"learn":[0.001736728557],"iteration":620,"passed_time":4.387748461,"remaining_time":2.677869029},
{"learn":[0.001736732258],"iteration":621,"passed_time":4.394236447,"remaining_time":2.670452375},
{"learn":[0.001736722441],"iteration":622,"passed_time":4.400859745,"remaining_time":2.663120584},
{"learn":[0.001736727672],"iteration":623,"passed_time":4.40830495,"remaining_time":2.656286316},
{"learn":[0.001736723648],"iteration":624,"passed_time":4.414717385,"remaining_time":2.648830431},
{"learn":[0.001736721154],"iteration":625,"passed_time":4.423188302,"remaining_time":2.642607708},
{"learn":[0.001736710533],"iteration":626,"passed_time":4.426323844,"remaining_time":2.633203818},
{"learn":[0.001736726062],"iteration":627,"passed_time":4.431957205,"remaining_time":2.625299491},
{"learn":[0.00173670828],"iteration":628,"passed_time":4.439307324,"remaining_time":2.618414972},
{"learn":[0.001736700072],"iteration":629,"passed_time":4.445196009,"remaining_time":2.610670672},
{"learn":[0.001736709969],"iteration":630,"passed_time":4.451608838,"remaining_time":2.603238766},
{"learn":[0.001736709808],"iteration":631,"passed_time":4.457293167,"remaining_time":2.595385895},
{"learn":[0.001736706268],"iteration":632,"passed_time":4.463487657,"remaining_time":2.587835656},
{"learn":[0.001736709165],"iteration":633,"passed_time":4.471369047,"remaining_time":2.581263519},
{"learn":[0.0017366979],"iteration":634,"passed_time":4.477485322,"remaining_time":2.573672665},
{"learn":[0.001736708682],"iteration":635,"passed_time":4.484467334,"remaining_time":2.566581933},
{"learn":[0.001736229672],"iteration":636,"passed_time":4.491149956,"remaining_time":2.559320933},
{"learn":[0.001736223396],"iteration":637,"passed_time":4.497697902,"remaining_time":2.55198533},
{"learn":[0.001736221465],"iteration":638,"passed_time":4.504605547,"remaining_time":2.544855403},
{"learn":[0.001736208188],"iteration":639,"passed_time":4.510913354,"remaining_time":2.537388762},
{"learn":[0.001736219453],"iteration":640,"passed_time":4.51716915,"remaining_time":2.529896607},
{"learn":[0.001736217844],"iteration":641,"passed_time":4.522745247,"remaining_time":2.522029281},
{"learn":[0.001736202153],"iteration":642,"passed_time":4.530144036,"remaining_time":2.515181059},
{"learn":[0.001736207705],"iteration":643,"passed_time":4.537122696,"remaining_time":2.508098882},
{"learn":[0.001736206096],"iteration":644,"passed_time":4.542286521,"remaining_time":2.500018163},
{"learn":[0.001734829979],"iteration":645,"passed_time":4.54833814,"remaining_time":2.492432974},
{"learn":[0.001734827324],"iteration":646,"passed_time":4.554889789,"remaining_time":2.485125341},
{"learn":[0.001734823461],"iteration":647,"passed_time":4.560008384,"remaining_time":2.477041591},
{"learn":[0.001734826519],"iteration":648,"passed_time":4.565612806,"remaining_time":2.46922973},
{"learn":[0.001734828933],"iteration":649,"passed_time":4.571523466,"remaining_time":2.461589559},
{"learn":[0.001734834163],"iteration":650,"passed_time":4.577156597,"remaining_time":2.453805917},
{"learn":[0.001734817185],"iteration":651,"passed_time":4.583639462,"remaining_time":2.446482412},
{"learn":[0.001734830703],"iteration":652,"passed_time":4.58900097,"remaining_time":2.4385656},
{"learn":[0.001734830945],"iteration":653,"passed_time":4.594475596,"remaining_time":2.430716447},
{"learn":[0.001734818955],"iteration":654,"passed_time":4.600367507,"remaining_time":2.423094336},
{"learn":[0.00173483014],"iteration":655,"passed_time":4.605324168,"remaining_time":2.414987064},
{"learn":[0.001734820806],"iteration":656,"passed_time":4.610766458,"remaining_time":2.407142915},
{"learn":[0.001734823703],"iteration":657,"passed_time":4.616652618,"remaining_time":2.399536771},
{"learn":[0.001734823703],"iteration":658,"passed_time":4.621771824,"remaining_time":2.391538986},
{"learn":[0.001734822335],"iteration":659,"passed_time":4.627290977,"remaining_time":2.383755958},
{"learn":[0.00173481976],"iteration":660,"passed_time":4.633308025,"remaining_time":2.376235129},
{"learn":[0.00173482322],"iteration":661,"passed_time":4.638526438,"remaining_time":2.368311082},
{"learn":[0.001734819599],"iteration":662,"passed_time":4.643944243,"remaining_time":2.360496546},
{"learn":[0.001734815334],"iteration":663,"passed_time":4.64931258,"remaining_time":2.352664197},
{"learn":[0.001734759009],"iteration":664,"passed_time":4.654572516,"remaining_time":2.344784651},
{"learn":[0.001734754503],"iteration":665,"passed_time":4.65991438,"remaining_time":2.336954059},
{"learn":[0.00173476263],"iteration":666,"passed_time":4.665376045,"remaining_time":2.329190739},
{"learn":[0.001734756675],"iteration":667,"passed_time":4.670484062,"remaining_time":2.321258546},
{"learn":[0.00173475579],"iteration":668,"passed_time":4.676203409,"remaining_time":2.313637262},
{"learn":[0.001734743237],"iteration":669,"passed_time":4.681859521,"remaining_time":2.30599051},
{"learn":[0.001734749675],"iteration":670,"passed_time":4.687020446,"remaining_time":2.298106895},
{"learn":[0.001734750077],"iteration":671,"passed_time":4.692458252,"remaining_time":2.290366528},
{"learn":[0.001734758284],"iteration":672,"passed_time":4.697939321,"remaining_time":2.282654024},
{"learn":[0.001734750318],"iteration":673,"passed_time":4.703179616,"remaining_time":2.274831684},
{"learn":[0.001734746054],"iteration":674,"passed_time":4.709982845,"remaining_time":2.267769518},
{"learn":[0.001734749675],"iteration":675,"passed_time":4.715146707,"remaining_time":2.259922386},
{"learn":[0.001734743801],"iteration":676,"passed_time":4.720345384,"remaining_time":2.252099792},
{"learn":[0.001734747341],"iteration":677,"passed_time":4.726205972,"remaining_time":2.244599297},
{"learn":[0.00173474018],"iteration":678,"passed_time":4.731407011,"remaining_time":2.236791827},
{"learn":[0.00173474018],"iteration":679,"passed_time":4.736414925,"remaining_time":2.228901141},
{"learn":[0.001734743398],"iteration":680,"passed_time":4.741897017,"remaining_time":2.22124104},
{"learn":[0.001734743398],"iteration":681,"passed_time":4.746827008,"remaining_time":2.213329895},
{"learn":[0.001734719098],"iteration":682,"passed_time":4.751954779,"remaining_time":2.205519275},
{"learn":[0.0017347298],"iteration":683,"passed_time":4.75620126,"remaining_time":2.197309354},
{"learn":[0.001734724409],"iteration":684,"passed_time":4.76189999,"remaining_time":2.189778828},
{"learn":[0.001734717408],"iteration":685,"passed_time":4.766972997,"remaining_time":2.181967232},
{"learn":[0.001734706706],"iteration":686,"passed_time":4.772226756,"remaining_time":2.17424596},
{"learn":[0.001734715557],"iteration":687,"passed_time":4.777584779,"remaining_time":2.166579144},
{"learn":[0.001734715557],"iteration":688,"passed_time":4.782310494,"remaining_time":2.158633619},
{"learn":[0.001734717006],"iteration":689,"passed_time":4.787135759,"remaining_time":2.150742152},
{"learn":[0.001734709522],"iteration":690,"passed_time":4.792709903,"remaining_time":2.143194443},
{"learn":[0.001734713868],"iteration":691,"passed_time":4.797744703,"remaining_time":2.135412382},
{"learn":[0.001734710408],"iteration":692,"passed_time":4.802612318,"remaining_time":2.127564187},
{"learn":[0.001734716603],"iteration":693,"passed_time":4.808493163,"remaining_time":2.120171337},
{"learn":[0.001734708798],"iteration":694,"passed_time":4.81384096,"remaining_time":2.112548911},
{"learn":[0.001734704855],"iteration":695,"passed_time":4.818742755,"remaining_time":2.104738215},
{"learn":[0.001734693188],"iteration":696,"passed_time":4.825036655,"remaining_time":2.097541042},
{"learn":[0.001734689567],"iteration":697,"passed_time":4.830263513,"remaining_time":2.089884787},
{"learn":[0.001734691981],"iteration":698,"passed_time":4.835181473,"remaining_time":2.082102466},
{"learn":[0.001734693027],"iteration":699,"passed_time":4.841159909,"remaining_time":2.074782818},
{"learn":[0.001734693993],"iteration":700,"passed_time":4.846366383,"remaining_time":2.06713773},
{"learn":[0.001734693993],"iteration":701,"passed_time":4.85135197,"remaining_time":2.059405822},
{"learn":[0.001734683934],"iteration":702,"passed_time":4.857321874,"remaining_time":2.052097577},
{"learn":[0.00173468659],"iteration":703,"passed_time":4.862266984,"remaining_time":2.044362255},
{"learn":[0.001734693751],"iteration":704,"passed_time":4.867092512,"remaining_time":2.03658481},
{"learn":[0.001734686751],"iteration":705,"passed_time":4.873214899,"remaining_time":2.02935578},
{"learn":[0.001734682084],"iteration":706,"passed_time":4.878190449,"remaining_time":2.021654599},
{"learn":[0.001734687153],"iteration":707,"passed_time":4.883245448,"remaining_time":2.013993885},
{"learn":[0.001734693671],"iteration":708,"passed_time":4.88893993,"remaining_time":2.00660299},
{"learn":[0.001734670336],"iteration":709,"passed_time":4.893817201,"remaining_time":1.998883082},
{"learn":[0.001734684981],"iteration":710,"passed_time":4.898738648,"remaining_time":1.991189127},
{"learn":[0.001734674761],"iteration":711,"passed_time":4.904975855,"remaining_time":1.984035177},
{"learn":[0.001734670497],"iteration":712,"passed_time":4.910059685,"remaining_time":1.976419537},
{"learn":[0.001734674118],"iteration":713,"passed_time":4.914940458,"remaining_time":1.968729651},
{"learn":[0.0017346676],"iteration":714,"passed_time":4.921007954,"remaining_time":1.961520653},
{"learn":[0.001734673635],"iteration":715,"passed_time":4.925922565,"remaining_time":1.953857554},
{"learn":[0.001734661887],"iteration":716,"passed_time":4.930942369,"remaining_time":1.946243641},
{"learn":[0.001734652633],"iteration":717,"passed_time":4.937861421,"remaining_time":1.939382898},
{"learn":[0.00173466414],"iteration":718,"passed_time":4.943878336,"remaining_time":1.932169419},
{"learn":[0.001734661565],"iteration":719,"passed_time":4.949255083,"remaining_time":1.92471031},
{"learn":[0.001734664703],"iteration":720,"passed_time":4.955334726,"remaining_time":1.917528972},
{"learn":[0.001734673796],"iteration":721,"passed_time":4.960661272,"remaining_time":1.910060711},
{"learn":[0.001734663577],"iteration":722,"passed_time":4.966237132,"remaining_time":1.902693894},
{"learn":[0.001734658668],"iteration":723,"passed_time":4.971864944,"remaining_time":1.89535183},
{"learn":[0.00173465384],"iteration":724,"passed_time":4.976889126,"remaining_time":1.88778553},
{"learn":[0.00173466237],"iteration":725,"passed_time":4.982258675,"remaining_time":1.88035658},
{"learn":[0.00173465899],"iteration":726,"passed_time":4.987579737,"remaining_time":1.872915087},
{"learn":[0.001734652794],"iteration":727,"passed_time":4.992511322,"remaining_time":1.865333901},
{"learn":[0.001734652794],"iteration":728,"passed_time":4.997413885,"remaining_time":1.857749195},
{"learn":[0.001734652794],"iteration":729,"passed_time":5.002663522,"remaining_time":1.850300207},
{"learn":[0.001734652794],"iteration":730,"passed_time":5.007475655,"remaining_time":1.84269624},
{"learn":[0.001734652955],"iteration":731,"passed_time":5.012479391,"remaining_time":1.83517005},
{"learn":[0.001734654243],"iteration":732,"passed_time":5.018036005,"remaining_time":1.827852133},
{"learn":[0.00173464684],"iteration":733,"passed_time":5.024063338,"remaining_time":1.820709602},
{"learn":[0.001734641449],"iteration":734,"passed_time":5.029382065,"remaining_time":1.813314622},
{"learn":[0.001734635333],"iteration":735,"passed_time":5.03532871,"remaining_time":1.806150515},
{"learn":[0.001734653116],"iteration":736,"passed_time":5.040235238,"remaining_time":1.798618545},
{"learn":[0.001734637023],"iteration":737,"passed_time":5.045247087,"remaining_time":1.79113108},
{"learn":[0.001734637104],"iteration":738,"passed_time":5.050960283,"remaining_time":1.783898016},
{"learn":[0.00173463646],"iteration":739,"passed_time":5.056001961,"remaining_time":1.776433121},
{"learn":[0.001734637184],"iteration":740,"passed_time":5.060769847,"remaining_time":1.768879069},
{"learn":[0.001734640725],"iteration":741,"passed_time":5.066337506,"remaining_time":1.761610615},
{"learn":[0.00173463646],"iteration":742,"passed_time":5.07153262,"remaining_time":1.754217878},
{"learn":[0.001734643139],"iteration":743,"passed_time":5.076570674,"remaining_time":1.746777006},
{"learn":[0.001734633966],"iteration":744,"passed_time":5.082411704,"remaining_time":1.739617429},
{"learn":[0.001734644265],"iteration":745,"passed_time":5.087481231,"remaining_time":1.732198703},
{"learn":[0.001734627126],"iteration":746,"passed_time":5.092510965,"remaining_time":1.72477279},
{"learn":[0.001734631632],"iteration":747,"passed_time":5.09810998,"remaining_time":1.717545073},
{"learn":[0.001734631632],"iteration":748,"passed_time":5.102925232,"remaining_time":1.710059056},
{"learn":[0.001734634207],"iteration":749,"passed_time":5.107917664,"remaining_time":1.702639221},
{"learn":[0.001734634207],"iteration":750,"passed_time":5.113311152,"remaining_time":1.695358824},
{"learn":[0.001734618355],"iteration":751,"passed_time":5.118390023,"remaining_time":1.687979689},
{"learn":[0.001734614332],"iteration":752,"passed_time":5.123403478,"remaining_time":1.680585204},
{"learn":[0.001734623505],"iteration":753,"passed_time":5.129547553,"remaining_time":1.673565913},
{"learn":[0.001734632839],"iteration":754,"passed_time":5.135006818,"remaining_time":1.666326716},
{"learn":[0.001734625195],"iteration":755,"passed_time":5.140348096,"remaining_time":1.659054148},
{"learn":[0.001734631069],"iteration":756,"passed_time":5.146981568,"remaining_time":1.652201481},
{"learn":[0.001734615861],"iteration":757,"passed_time":5.152436234,"remaining_time":1.644973046},
{"learn":[0.00173461232],"iteration":758,"passed_time":5.157254176,"remaining_time":1.63754711},
{"learn":[0.001734615137],"iteration":759,"passed_time":5.163881748,"remaining_time":1.630699499},
{"learn":[0.001734618758],"iteration":760,"passed_time":5.169624089,"remaining_time":1.623574451},
{"learn":[0.001734624471],"iteration":761,"passed_time":5.175371635,"remaining_time":1.616454658},
{"learn":[0.001734632598],"iteration":762,"passed_time":5.182640828,"remaining_time":1.609811109},
{"learn":[0.001734622057],"iteration":763,"passed_time":5.188482583,"remaining_time":1.602724986},
{"learn":[0.001734622459],"iteration":764,"passed_time":5.195686831,"remaining_time":1.596060661},
{"learn":[0.001734622781],"iteration":765,"passed_time":5.201386621,"remaining_time":1.588935338},
{"learn":[0.001734619321],"iteration":766,"passed_time":5.207101901,"remaining_time":1.581818439},
{"learn":[0.001734622379],"iteration":767,"passed_time":5.213601537,"remaining_time":1.574942131},
{"learn":[0.001734615137],"iteration":768,"passed_time":5.219390783,"remaining_time":1.567853408},
{"learn":[0.001734621976],"iteration":769,"passed_time":5.225822375,"remaining_time":1.56095993},
{"learn":[0.001734617551],"iteration":770,"passed_time":5.230938162,"remaining_time":1.553676834},
{"learn":[0.001734622539],"iteration":771,"passed_time":5.23646155,"remaining_time":1.546519732},
{"learn":[0.00173461393],"iteration":772,"passed_time":5.241748244,"remaining_time":1.53929735},
{"learn":[0.001734616666],"iteration":773,"passed_time":5.246777968,"remaining_time":1.532004936},
{"learn":[0.001734604596],"iteration":774,"passed_time":5.252034978,"remaining_time":1.524784348},
{"learn":[0.001734604596],"iteration":775,"passed_time":5.257651159,"remaining_time":1.517672499},
{"learn":[0.001734606607],"iteration":776,"passed_time":5.262600447,"remaining_time":1.510373101},
{"learn":[0.00173460363],"iteration":777,"passed_time":5.267871834,"remaining_time":1.503171654},
{"learn":[0.001734602504],"iteration":778,"passed_time":5.27354466,"remaining_time":1.49608905},
{"learn":[0.001734593974],"iteration":779,"passed_time":5.278696643,"remaining_time":1.488863156},
{"learn":[0.001734588905],"iteration":780,"passed_time":5.284232817,"remaining_time":1.481750303},
{"learn":[0.001734597837],"iteration":781,"passed_time":5.289783756,"remaining_time":1.4746456},
{"learn":[0.00173459317],"iteration":782,"passed_time":5.295100941,"remaining_time":1.467480082},
{"learn":[0.001734587215],"iteration":783,"passed_time":5.300175281,"remaining_time":1.460252373},
{"learn":[0.001734596871],"iteration":784,"passed_time":5.305727872,"remaining_time":1.453161137},
{"learn":[0.001734602021],"iteration":785,"passed_time":5.31132445,"remaining_time":1.446085792},
{"learn":[0.001734596791],"iteration":786,"passed_time":5.317368145,"remaining_time":1.439135216},
{"learn":[0.001734590112],"iteration":787,"passed_time":5.322985266,"remaining_time":1.432072178},
{"learn":[0.001734593089],"iteration":788,"passed_time":5.32823178,"remaining_time":1.424913695},
{"learn":[0.001734602182],"iteration":789,"passed_time":5.334135463,"remaining_time":1.417934743},
{"learn":[0.001734602182],"iteration":790,"passed_time":5.339158917,"remaining_time":1.410725934},
{"learn":[0.001734577238],"iteration":791,"passed_time":5.344431349,"remaining_time":1.403588031},
{"learn":[0.001734579571],"iteration":792,"passed_time":5.350339034,"remaining_time":1.396620656},
{"learn":[0.001734590595],"iteration":793,"passed_time":5.355772984,"remaining_time":1.389533041},
{"learn":[0.001734591721],"iteration":794,"passed_time":5.360856595,"remaining_time":1.382359248},
{"learn":[0.001734571927],"iteration":795,"passed_time":5.366561307,"remaining_time":1.375349883},
{"learn":[0.001734575628],"iteration":796,"passed_time":5.372197062,"remaining_time":1.368326228},
{"learn":[0.001734567099],"iteration":797,"passed_time":5.37751607,"remaining_time":1.361225872},
{"learn":[0.001734577479],"iteration":798,"passed_time":5.38358817,"remaining_time":1.354319427},
{"learn":[0.00173458118],"iteration":799,"passed_time":5.388923127,"remaining_time":1.347230782},
{"learn":[0.001734578605],"iteration":800,"passed_time":5.394200421,"remaining_time":1.340132189},
{"learn":[0.001734574743],"iteration":801,"passed_time":5.400216898,"remaining_time":1.333220631},
{"learn":[0.001734582629],"iteration":802,"passed_time":5.405321272,"remaining_time":1.326087535},
{"learn":[0.001734566053],"iteration":803,"passed_time":5.410184143,"remaining_time":1.318900612},
{"learn":[0.001734575467],"iteration":804,"passed_time":5.416717762,"remaining_time":1.312124178},
{"learn":[0.00173456557],"iteration":805,"passed_time":5.421748607,"remaining_time":1.304986638},
{"learn":[0.001734562915],"iteration":806,"passed_time":5.426669276,"remaining_time":1.297827968},
{"learn":[0.001734572168],"iteration":807,"passed_time":5.433009494,"remaining_time":1.291012157},
{"learn":[0.001734573134],"iteration":808,"passed_time":5.438116112,"remaining_time":1.283906276},
{"learn":[0.001734565007],"iteration":809,"passed_time":5.443168012,"remaining_time":1.276792497},
{"learn":[0.001734566697],"iteration":810,"passed_time":5.450304524,"remaining_time":1.270169612},
{"learn":[0.001734565892],"iteration":811,"passed_time":5.455667798,"remaining_time":1.263134909},
{"learn":[0.001734563156],"iteration":812,"passed_time":5.462412829,"remaining_time":1.256422139},
{"learn":[0.001734564122],"iteration":813,"passed_time":5.471832555,"remaining_time":1.250320461},
{"learn":[0.001734561949],"iteration":814,"passed_time":5.481004256,"remaining_time":1.24415434},
{"learn":[0.00173456734],"iteration":815,"passed_time":5.488153283,"remaining_time":1.23752476},
{"learn":[0.001734554788],"iteration":816,"passed_time":5.498252335,"remaining_time":1.231554684},
{"learn":[0.001734546258],"iteration":817,"passed_time":5.505784729,"remaining_time":1.225003448},
{"learn":[0.001734538695],"iteration":818,"passed_time":5.514530186,"remaining_time":1.218717904},
{"learn":[0.00173453451],"iteration":819,"passed_time":5.521806392,"remaining_time":1.212103842},
{"learn":[0.001734540948],"iteration":820,"passed_time":5.530711744,"remaining_time":1.205843364},
{"learn":[0.001734537488],"iteration":821,"passed_time":5.538221036,"remaining_time":1.199274142},
{"learn":[0.001734539741],"iteration":822,"passed_time":5.547213089,"remaining_time":1.193021527},
{"learn":[0.00173454658],"iteration":823,"passed_time":5.554181593,"remaining_time":1.186330049},
{"learn":[0.001734537327],"iteration":824,"passed_time":5.56150299,"remaining_time":1.179712756},
{"learn":[0.001734540224],"iteration":825,"passed_time":5.570388079,"remaining_time":1.173423155},
{"learn":[0.001734539419],"iteration":826,"passed_time":5.578690665,"remaining_time":1.167005423},
{"learn":[0.001734540706],"iteration":827,"passed_time":5.590487054,"remaining_time":1.161308905},
{"learn":[0.001734531775],"iteration":828,"passed_time":5.597432997,"remaining_time":1.154597156},
{"learn":[0.001734535476],"iteration":829,"passed_time":5.60419097,"remaining_time":1.147846343},
{"learn":[0.001734528637],"iteration":830,"passed_time":5.61141298,"remaining_time":1.141189884},
{"learn":[0.001734530407],"iteration":831,"passed_time":5.617688211,"remaining_time":1.134340889},
{"learn":[0.00173453097],"iteration":832,"passed_time":5.624100652,"remaining_time":1.127520779},
{"learn":[0.001734533947],"iteration":833,"passed_time":5.632679909,"remaining_time":1.121132931},
{"learn":[0.00173451536],"iteration":834,"passed_time":5.642740805,"remaining_time":1.115032614},
{"learn":[0.001734524613],"iteration":835,"passed_time":5.649161532,"remaining_time":1.108208722},
{"learn":[0.001734531775],"iteration":836,"passed_time":5.65506677,"remaining_time":1.101285404},
{"learn":[0.001734530729],"iteration":837,"passed_time":5.661860646,"remaining_time":1.094536306},
{"learn":[0.001734533384],"iteration":838,"passed_time":5.66789127,"remaining_time":1.087640637},
{"learn":[0.001734530085],"iteration":839,"passed_time":5.675046984,"remaining_time":1.08096133},
{"learn":[0.001734538695],"iteration":840,"passed_time":5.680939119,"remaining_time":1.074041998},
{"learn":[0.001734542959],"iteration":841,"passed_time":5.686529846,"remaining_time":1.067068546},
{"learn":[0.00173452582],"iteration":842,"passed_time":5.693654239,"remaining_time":1.060384004},
{"learn":[0.001734521073],"iteration":843,"passed_time":5.699374127,"remaining_time":1.05343882},
{"learn":[0.001734534752],"iteration":844,"passed_time":5.7062531,"remaining_time":1.046709149},
{"learn":[0.001734526786],"iteration":845,"passed_time":5.712421712,"remaining_time":1.039849815},
{"learn":[0.001734530165],"iteration":846,"passed_time":5.718514608,"remaining_time":1.032978436},
{"learn":[0.001734526947],"iteration":847,"passed_time":5.726468071,"remaining_time":1.02644239},
{"learn":[0.001734513911],"iteration":848,"passed_time":5.732287913,"remaining_time":1.019523527},
{"learn":[0.001734520349],"iteration":849,"passed_time":5.73900767,"remaining_time":1.012766059},
{"learn":[0.001734512141],"iteration":850,"passed_time":5.744748967,"remaining_time":1.005837363},
{"learn":[0.001734528315],"iteration":851,"passed_time":5.750648966,"remaining_time":0.9989390223},
{"learn":[0.001734526866],"iteration":852,"passed_time":5.758233452,"remaining_time":0.9923333147},
{"learn":[0.001734520429],"iteration":853,"passed_time":5.76530327,"remaining_time":0.9856373271},
{"learn":[0.001734515843],"iteration":854,"passed_time":5.773695504,"remaining_time":0.9791647346},
{"learn":[0.001734507555],"iteration":855,"passed_time":5.782399299,"remaining_time":0.972740069},
{"learn":[0.00173451029],"iteration":856,"passed_time":5.790350406,"remaining_time":0.9661844901},
{"learn":[0.001734507072],"iteration":857,"passed_time":5.796563344,"remaining_time":0.9593379893},
{"learn":[0.001734511176],"iteration":858,"passed_time":5.804485814,"remaining_time":0.9527735736},
{"learn":[0.001734513831],"iteration":859,"passed_time":5.81072838,"remaining_time":0.9459325269},
{"learn":[0.001734510934],"iteration":860,"passed_time":5.817118515,"remaining_time":0.939116694},
{"learn":[0.001734493151],"iteration":861,"passed_time":5.826360582,"remaining_time":0.9327584227},
{"learn":[0.001734496853],"iteration":862,"passed_time":5.8345235,"remaining_time":0.9262221547},
{"learn":[0.001734488404],"iteration":863,"passed_time":5.842684901,"remaining_time":0.9196818825},
{"learn":[0.001734500876],"iteration":864,"passed_time":5.849472178,"remaining_time":0.9129234036},
{"learn":[0.00173449806],"iteration":865,"passed_time":5.856241245,"remaining_time":0.9061620401},
{"learn":[0.001734491462],"iteration":866,"passed_time":5.862462076,"remaining_time":0.8993165583},
{"learn":[0.001734495404],"iteration":867,"passed_time":5.87104611,"remaining_time":0.892831897},
{"learn":[0.001734495324],"iteration":868,"passed_time":5.878617974,"remaining_time":0.8861898212},
{"learn":[0.001734494519],"iteration":869,"passed_time":5.890215652,"remaining_time":0.8801471664},
{"learn":[0.001734492105],"iteration":870,"passed_time":5.896438559,"remaining_time":0.8732957223},
{"learn":[0.001734488887],"iteration":871,"passed_time":5.904580959,"remaining_time":0.8667274803},
{"learn":[0.001734488484],"iteration":872,"passed_time":5.910101742,"remaining_time":0.8597742512},
{"learn":[0.001734492508],"iteration":873,"passed_time":5.917056296,"remaining_time":0.8530309992},
{"learn":[0.001734480196],"iteration":874,"passed_time":5.922855496,"remaining_time":0.8461222136},
{"learn":[0.001734482932],"iteration":875,"passed_time":5.928760518,"remaining_time":0.8392309409},
{"learn":[0.001734480277],"iteration":876,"passed_time":5.936886429,"remaining_time":0.8326533989},
{"learn":[0.001734482128],"iteration":877,"passed_time":5.943867795,"remaining_time":0.8259132926},
{"learn":[0.001734485909],"iteration":878,"passed_time":5.953563943,"remaining_time":0.8195463449},
{"learn":[0.001734485185],"iteration":879,"passed_time":5.960305274,"remaining_time":0.812768901},
{"learn":[0.001734473357],"iteration":880,"passed_time":5.970801537,"remaining_time":0.8064987321},
{"learn":[0.001734475449],"iteration":881,"passed_time":5.976789374,"remaining_time":0.799615812},
{"learn":[0.00173448084],"iteration":882,"passed_time":5.985334641,"remaining_time":0.793073786},
{"learn":[0.001734467563],"iteration":883,"passed_time":5.992021379,"remaining_time":0.7862833483},
{"learn":[0.001734471104],"iteration":884,"passed_time":5.999674289,"remaining_time":0.7796186929},
{"learn":[0.001734473679],"iteration":885,"passed_time":6.007611129,"remaining_time":0.7729883394},
{"learn":[0.001734467885],"iteration":886,"passed_time":6.022345441,"remaining_time":0.7672210088},
{"learn":[0.001734464103],"iteration":887,"passed_time":6.029179805,"remaining_time":0.7604370926},
{"learn":[0.001734460965],"iteration":888,"passed_time":6.035954302,"remaining_time":0.7536455877},
{"learn":[0.001734481645],"iteration":889,"passed_time":6.042244486,"remaining_time":0.7467942623},
{"learn":[0.001734473357],"iteration":890,"passed_time":6.051661522,"remaining_time":0.7403267182},
{"learn":[0.001734463701],"iteration":891,"passed_time":6.06087555,"remaining_time":0.7338279814},
{"learn":[0.001734464667],"iteration":892,"passed_time":6.068544717,"remaining_time":0.7271380567},
{"learn":[0.001734462092],"iteration":893,"passed_time":6.078486085,"remaining_time":0.7207153524},
{"learn":[0.001734469977],"iteration":894,"passed_time":6.084559647,"remaining_time":0.71383102},
{"learn":[0.001734458873],"iteration":895,"passed_time":6.090452278,"remaining_time":0.7069274966},
{"learn":[0.001734464988],"iteration":896,"passed_time":6.098034965,"remaining_time":0.7002202915},
{"learn":[0.001734457103],"iteration":897,"passed_time":6.10460138,"remaining_time":0.6933957024},
{"learn":[0.001734451309],"iteration":898,"passed_time":6.113502331,"remaining_time":0.686833966},
{"learn":[0.001734448574],"iteration":899,"passed_time":6.120645949,"remaining_time":0.6800717721},
{"learn":[0.001734461368],"iteration":900,"passed_time":6.129773209,"remaining_time":0.67352669},
{"learn":[0.001734452436],"iteration":901,"passed_time":6.136458365,"remaining_time":0.6667105541},
{"learn":[0.001734458068],"iteration":902,"passed_time":6.146758243,"remaining_time":0.6602830006},
{"learn":[0.00173446354],"iteration":903,"passed_time":6.154242369,"remaining_time":0.6535478622},
{"learn":[0.001734461287],"iteration":904,"passed_time":6.162586172,"remaining_time":0.6469013109},
{"learn":[0.001734447528],"iteration":905,"passed_time":6.169050924,"remaining_time":0.6400560561},
{"learn":[0.001734452114],"iteration":906,"passed_time":6.177090063,"remaining_time":0.6333730715},
{"learn":[0.0017344497],"iteration":907,"passed_time":6.183920112,"remaining_time":0.6265645929},
{"learn":[0.001734450907],"iteration":908,"passed_time":6.190494532,"remaining_time":0.6197304757},
{"learn":[0.001734456218],"iteration":909,"passed_time":6.197005508,"remaining_time":0.6128906547},
{"learn":[0.001734457103],"iteration":910,"passed_time":6.203214475,"remaining_time":0.6060220508},
{"learn":[0.001734448332],"iteration":911,"passed_time":6.210797595,"remaining_time":0.5992874872},
{"learn":[0.001734450183],"iteration":912,"passed_time":6.217565418,"remaining_time":0.592473375},
{"learn":[0.001734452275],"iteration":913,"passed_time":6.225187231,"remaining_time":0.5857397175},
{"learn":[0.001734443585],"iteration":914,"passed_time":6.232138813,"remaining_time":0.5789418569},
{"learn":[0.001734444309],"iteration":915,"passed_time":6.239756199,"remaining_time":0.5722047169},
{"learn":[0.001734436826],"iteration":916,"passed_time":6.24622895,"remaining_time":0.5653620532},
{"learn":[0.001734444309],"iteration":917,"passed_time":6.254773795,"remaining_time":0.5587052845},
{"learn":[0.001734447286],"iteration":918,"passed_time":6.262938475,"remaining_time":0.5520108993},
{"learn":[0.001734444872],"iteration":919,"passed_time":6.273221284,"remaining_time":0.5454975029},
{"learn":[0.001734448091],"iteration":920,"passed_time":6.280928886,"remaining_time":0.5387550293},
{"learn":[0.001734440688],"iteration":921,"passed_time":6.289367888,"remaining_time":0.5320723376},
{"learn":[0.001734435216],"iteration":922,"passed_time":6.296513451,"remaining_time":0.5252779369},
{"learn":[0.001734433768],"iteration":923,"passed_time":6.304001501,"remaining_time":0.518510946},
{"learn":[0.001734439803],"iteration":924,"passed_time":6.311468876,"remaining_time":0.5117407197},
{"learn":[0.001734437872],"iteration":925,"passed_time":6.319160889,"remaining_time":0.5049869393},
{"learn":[0.001734437952],"iteration":926,"passed_time":6.32652238,"remaining_time":0.4982051066},
{"learn":[0.001734426204],"iteration":927,"passed_time":6.33360543,"remaining_time":0.4914004213},
{"learn":[0.001734438194],"iteration":928,"passed_time":6.341230509,"remaining_time":0.4846365621},
{"learn":[0.001734431998],"iteration":929,"passed_time":6.347086712,"remaining_time":0.4777377095},
{"learn":[0.001734441332],"iteration":930,"passed_time":6.354364729,"remaining_time":0.470946473},
{"learn":[0.001734433688],"iteration":931,"passed_time":6.360359136,"remaining_time":0.4640605378},
{"learn":[0.001734433607],"iteration":932,"passed_time":6.367510666,"remaining_time":0.4572596084},
{"learn":[0.001734432963],"iteration":933,"passed_time":6.377249951,"remaining_time":0.4506407888},
{"learn":[0.001734431676],"iteration":934,"passed_time":6.391683283,"remaining_time":0.4443416186},
{"learn":[0.001734418882],"iteration":935,"passed_time":6.398720782,"remaining_time":0.4375193697},
{"learn":[0.001734422101],"iteration":936,"passed_time":6.406423321,"remaining_time":0.4307413759},
{"learn":[0.00173439088],"iteration":937,"passed_time":6.413440785,"remaining_time":0.4239161287},
{"learn":[0.001734380098],"iteration":938,"passed_time":6.420759264,"remaining_time":0.4171100267},
{"learn":[0.001734385489],"iteration":939,"passed_time":6.427246414,"remaining_time":0.4102497711},
{"learn":[0.001734381626],"iteration":940,"passed_time":6.43554126,"remaining_time":0.4035036497},
{"learn":[0.00173438919],"iteration":941,"passed_time":6.441801522,"remaining_time":0.3966289684},
{"learn":[0.001734382753],"iteration":942,"passed_time":6.448298167,"remaining_time":0.3897698786},
{"learn":[0.001734387742],"iteration":943,"passed_time":6.454293169,"remaining_time":0.3828817981},
{"learn":[0.001734381224],"iteration":944,"passed_time":6.460322756,"remaining_time":0.3759976207},
{"learn":[0.001734377442],"iteration":945,"passed_time":6.467643984,"remaining_time":0.36918898},
{"learn":[0.001734391202],"iteration":946,"passed_time":6.473760085,"remaining_time":0.3623118104},
{"learn":[0.001734377845],"iteration":947,"passed_time":6.480822748,"remaining_time":0.3554881676},
{"learn":[0.001734375753],"iteration":948,"passed_time":6.487428905,"remaining_time":0.348639488},
{"learn":[0.001734372614],"iteration":949,"passed_time":6.4948865,"remaining_time":0.3418361316},
{"learn":[0.001734370603],"iteration":950,"passed_time":6.50327669,"remaining_time":0.3350794509},
{"learn":[0.001734382592],"iteration":951,"passed_time":6.510288432,"remaining_time":0.3282498369},
{"learn":[0.001734373097],"iteration":952,"passed_time":6.517402122,"remaining_time":0.3214248686},
{"learn":[0.001734368752],"iteration":953,"passed_time":6.526893908,"remaining_time":0.314713962},
{"learn":[0.001734377603],"iteration":954,"passed_time":6.53692426,"remaining_time":0.3080226091},
{"learn":[0.001734364487],"iteration":955,"passed_time":6.544736177,"remaining_time":0.3012221671},
{"learn":[0.001734366338],"iteration":956,"passed_time":6.552753495,"remaining_time":0.2944288404},
{"learn":[0.00173437012],"iteration":957,"passed_time":6.561070782,"remaining_time":0.2876461095},
{"learn":[0.001734371488],"iteration":958,"passed_time":6.570596972,"remaining_time":0.2809118622},
{"learn":[0.001734366177],"iteration":959,"passed_time":6.581525872,"remaining_time":0.2742302447},
{"learn":[0.001734353946],"iteration":960,"passed_time":6.588705096,"remaining_time":0.2673876158},
{"learn":[0.001734352257],"iteration":961,"passed_time":6.596935527,"remaining_time":0.2605858108},
{"learn":[0.001734354912],"iteration":962,"passed_time":6.604044206,"remaining_time":0.2537379394},
{"learn":[0.001734358452],"iteration":963,"passed_time":6.612382286,"remaining_time":0.2469354381},
{"learn":[0.001734349521],"iteration":964,"passed_time":6.619007518,"remaining_time":0.2400676302},
{"learn":[0.001734359096],"iteration":965,"passed_time":6.627985609,"remaining_time":0.2332831374},
{"learn":[0.001734354268],"iteration":966,"passed_time":6.637508428,"remaining_time":0.2265126971},
{"learn":[0.001734343647],"iteration":967,"passed_time":6.648866293,"remaining_time":0.2197972328},
{"learn":[0.001734341635],"iteration":968,"passed_time":6.659759061,"remaining_time":0.2130573074},
{"learn":[0.001734356441],"iteration":969,"passed_time":6.667481977,"remaining_time":0.2062107828},
{"learn":[0.001734348475],"iteration":970,"passed_time":6.677070085,"remaining_time":0.1994181591},
{"learn":[0.001734343888],"iteration":971,"passed_time":6.684045262,"remaining_time":0.1925445137},
{"learn":[0.001734341313],"iteration":972,"passed_time":6.695444924,"remaining_time":0.1857934357},
{"learn":[0.00173432337],"iteration":973,"passed_time":6.704155205,"remaining_time":0.1789610219},
{"learn":[0.001734320714],"iteration":974,"passed_time":6.712951396,"remaining_time":0.1721269589},
{"learn":[0.001734309127],"iteration":975,"passed_time":6.720248302,"remaining_time":0.1652520074},
{"learn":[0.00173429408],"iteration":976,"passed_time":6.728358098,"remaining_time":0.1583953288},
{"learn":[0.001734302931],"iteration":977,"passed_time":6.735322531,"remaining_time":0.1515103228},
{"learn":[0.001734298586],"iteration":978,"passed_time":6.744840572,"remaining_time":0.1446799305},
{"learn":[0.00173430269],"iteration":979,"passed_time":6.753219273,"remaining_time":0.1378208015},
{"learn":[0.001734299391],"iteration":980,"passed_time":6.763715888,"remaining_time":0.1309995942},
{"learn":[0.001734297299],"iteration":981,"passed_time":6.772075733,"remaining_time":0.1241317344},
{"learn":[0.001734287724],"iteration":982,"passed_time":6.781769731,"remaining_time":0.1172839119},
{"learn":[0.001734290862],"iteration":983,"passed_time":6.797998795,"remaining_time":0.1105365658},
{"learn":[0.001734291103],"iteration":984,"passed_time":6.814342927,"remaining_time":0.1037717197},
{"learn":[0.001734279355],"iteration":985,"passed_time":6.834758322,"remaining_time":0.09704525001},
{"learn":[0.001734275815],"iteration":986,"passed_time":6.844607597,"remaining_time":0.09015187311},
{"learn":[0.001734274849],"iteration":987,"passed_time":6.856481291,"remaining_time":0.0832771007},
{"learn":[0.001734278711],"iteration":988,"passed_time":6.866824944,"remaining_time":0.0763752016},
{"learn":[0.00173427163],"iteration":989,"passed_time":6.877967507,"remaining_time":0.06947441926},
{"learn":[0.001734271791],"iteration":990,"passed_time":6.886939156,"remaining_time":0.06254536065},
{"learn":[0.001734270102],"iteration":991,"passed_time":6.893704765,"remaining_time":0.05559439327},
{"learn":[0.001734273642],"iteration":992,"passed_time":6.903858422,"remaining_time":0.04866768273},
{"learn":[0.001734274366],"iteration":993,"passed_time":6.913207615,"remaining_time":0.04172962343},
{"learn":[0.001734267688],"iteration":994,"passed_time":6.924443127,"remaining_time":0.03479619662},
{"learn":[0.001734273964],"iteration":995,"passed_time":6.931144446,"remaining_time":0.02783592147},
{"learn":[0.001734266078],"iteration":996,"passed_time":6.939098631,"remaining_time":0.0208799357},
{"learn":[0.001734270826],"iteration":997,"passed_time":6.945727924,"remaining_time":0.01391929444},
{"learn":[0.001734270826],"iteration":998,"passed_time":6.952654569,"remaining_time":0.006959614183},
{"learn":[0.001734271309],"iteration":999,"passed_time":6.960732435,"remaining_time":0}
]}